reduced_risc_v/control_unit/SignExtend.sv
module SignExtend #(
    parameter DATA_WIDTH = 32
)(
    input logic [DATA_WIDTH-1:0]        instr,
    input logic [1:0]                   ImmSrc,
    output logic [DATA_WIDTH-1:0]        ImmOp
);

always_comb 
    case (ImmSrc)
    2'b01: ImmOp = {{DATA_WIDTH-12{instr[31]}}, instr[31:20]}; //I instruction
                    //20                        1           6              4        1      = 32 bits          
    2'b11: ImmOp = {{DATA_WIDTH-12{instr[31]}}, instr[7], instr[30:25], instr[11:8], 1'b0}; //B instructions

    default ImmOp = 32'b0;
    
    endcase 
endmodule

reduced_risc_v/control_unit/InstrMem.sv
module InstrMem #(
    parameter ADDRESS_WIDTH = 8,
    DATA_WIDTH = 8
    
)(
    input logic                     clk,
    input logic [ADDRESS_WIDTH-1:0] addr,
    output logic [31:0]   dout
);

logic [DATA_WIDTH-1:0] rom_array [2**ADDRESS_WIDTH-1:0];

initial begin
        $display("Loading rom.");
        $readmemh("machinecode.mem", rom_array);
end;


assign dout = {{rom_array[addr+3]}, {rom_array[addr+2]}, {rom_array[addr+1]}, {rom_array[addr]}};

endmodule

reduced_risc_v/control_unit/ControlUnit.sv
module ControlUnit #(
    parameter DATA_WIDTH = 32
)(
     input logic                         EQ,
     input logic [DATA_WIDTH-1:0]        instr,
     output logic                        RegWrite,
     output logic [2:0]                  ALUctrl,
     output logic                        ALUsrc,
     output logic [1:0]                 ImmSrc, 
     output logic                        PCsrc,
);
    //for ImmSrc
    //R => 00
    //I => 01
    //J => 10
    //B => 11

    /*
    3'b000: SUM = ALUop1 + ALUop2;
    3'b001: SUM = ALUop1 - ALUop2;
    3'b010: SUM = ALUop1 & ALUop2;
    3'b011: SUM = ALUop1 | ALUop2;
    3'b100: SUM = ALUop1 ^ ALUop2;
    */
    
    logic [6:0] opcode = instr[6:0];
    

    always_comb 
    case (opcode)
    7'b0010011: begin //addi instruction
        RegWrite = 1;
        ALUctrl = 3'b000;
        ALUsrc = 1;
        ImmSrc = 2'b01;
        PCsrc = 0;

    end
    7'b1100011: begin //bne instruction
        RegWrite = 0;
        ALUctrl = 3'b000;
        ALUsrc = 0;
        ImmSrc = 2'b11;
        PCsrc = EQ;

    end
        default begin //just in case we have something else
        RegWrite = 1;
        ALUctrl = 3'b000;
        ALUsrc = 1;
        ImmSrc = 2'b00;
        PCsrc = 0;

    end
    endcase 
    
endmodule

reduced_risc_v/control_unit/green.sv
module green #(
    parameter   ADDRESS_WIDTH = 8,
                DATA_WIDTH = 32
)(
     input logic [ADDRESS_WIDTH-1:0]     PC, //8b
     input logic                        EQ, //1b
     output logic [DATA_WIDTH-1:0]       instr,//32b
     output logic                        RegWrite, //1b
     output logic [2:0]                  ALUctrl, //3b
     output logic                        ALUsrc, //1 bit
     output logic                        PCsrc, //1 bit
     output logic [DATA_WIDTH-1:0]        ImmOp //32 bits
);

    logic [1:0]                        ImmSrc;

ControlUnit MyControlUnit(
    .EQ(EQ),
    .instr(instr),
    .RegWrite(RegWrite),
    .ALUctrl(ALUctrl),
    .ALUsrc(ALUsrc),
    .ImmSrc(ImmSrc),
    .PCsrc(PCsrc),
);

InstrMem MyInstrMem(
    .addr(PC),
    .dout(instr)
);

SignExtend MySignExtend(
    .instr(instr),
    .ImmSrc(ImmSrc),
    .ImmOp(ImmOp)
);

endmodule

reduced_risc_v/control_unit/Vgreen.vcd
$version Generated by VerilatedVcd $end
$date Fri Dec  1 15:01:54 2023 $end
$timescale 1ps $end

 $scope module TOP $end
  $var wire  3 ' ALUctrl [2:0] $end
  $var wire  1 ( ALUsrc $end
  $var wire  1 $ EQ $end
  $var wire 32 * ImmOp [31:0] $end
  $var wire  8 # PC [7:0] $end
  $var wire  1 ) PCsrc $end
  $var wire  1 & RegWrite $end
  $var wire 32 % instr [31:0] $end
  $scope module green $end
   $var wire 32 - ADDRESS_WIDTH [31:0] $end
   $var wire  3 ' ALUctrl [2:0] $end
   $var wire  1 ( ALUsrc $end
   $var wire 32 . DATA_WIDTH [31:0] $end
   $var wire  1 $ EQ $end
   $var wire 32 * ImmOp [31:0] $end
   $var wire  2 + ImmSrc [1:0] $end
   $var wire  8 # PC [7:0] $end
   $var wire  1 ) PCsrc $end
   $var wire  1 & RegWrite $end
   $var wire 32 % instr [31:0] $end
   $scope module MyControlUnit $end
    $var wire  3 ' ALUctrl [2:0] $end
    $var wire  1 ( ALUsrc $end
    $var wire 32 . DATA_WIDTH [31:0] $end
    $var wire  1 $ EQ $end
    $var wire  2 + ImmSrc [1:0] $end
    $var wire  1 ) PCsrc $end
    $var wire  1 & RegWrite $end
    $var wire 32 % instr [31:0] $end
    $var wire  7 , opcode [6:0] $end
   $upscope $end
   $scope module MyInstrMem $end
    $var wire 32 - ADDRESS_WIDTH [31:0] $end
    $var wire 32 - DATA_WIDTH [31:0] $end
    $var wire  8 # addr [7:0] $end
    $var wire  1 / clk $end
    $var wire 32 % dout [31:0] $end
   $upscope $end
   $scope module MySignExtend $end
    $var wire 32 . DATA_WIDTH [31:0] $end
    $var wire 32 * ImmOp [31:0] $end
    $var wire  2 + ImmSrc [1:0] $end
    $var wire 32 % instr [31:0] $end
   $upscope $end
  $upscope $end
 $upscope $end
$enddefinitions $end


#0
b00000000 #
0$
b00000000000000000000000000000000 %
0&
b000 '
0(
0)
b00000000000000000000000000000000 *
b00 +
b0000000 ,
b00000000000000000000000000001000 -
b00000000000000000000000000100000 .
0/
#2
b00001111111100000000001100010011 %
1&
1(
b00000000000000000000000011111111 *
b01 +
b0010011 ,
#4
b00000100 #
#6
b00001000 #
b00000000000000000000010100010011 %
b00000000000000000000000000000000 *
#8
b00001100 #
b00000000000000000000010110010011 %
#10
b00010000 #
b00000000000001011000010100010011 %
#12
b00010100 #
b00000000000101011000010110010011 %
b00000000000000000000000000000001 *
#14
b00011000 #
b11111110011001011001110011100011 %
0&
0(
b11111111111111111111111111111000 *
b11 +
b1100011 ,
#16
b00011100 #
b11111110000000110001100011100011 %
b11111111111111111111111111110000 *
#18
b00100000 #
b00000000000000000000000000000000 %
1&
1(
b00000000000000000000000000000000 *
b00 +
b0000000 ,
