reduced_risc_v/alu/alu.sv
module alu #(
    parameter DATA_WIDTH = 32
)(
    input logic [2:0] ALUctrl,
    input logic [DATA_WIDTH-1:0] ALUop1,
    input logic [DATA_WIDTH-1:0] ALUop2,
    output logic [DATA_WIDTH-1:0] SUM,
    output logic EQ
);

always_comb begin
    case (ALUctrl)
    3'b000: SUM = ALUop1 + ALUop2;
    3'b001: SUM = ALUop1 - ALUop2;
    3'b010: SUM = ALUop1 & ALUop2;
    3'b011: SUM = ALUop1 | ALUop2;
    3'b100: SUM = ALUop1 ^ ALUop2;

    default: SUM = 0;

    endcase 

    assign EQ = (ALUop1 == ALUop2);

end 

endmodule

reduced_risc_v/cpu_test_old/mux2.sv
module mux2 #(
    parameter DATA_WIDTH = 32
)(
    input logic [DATA_WIDTH-1:0] regOp2,
    input logic [DATA_WIDTH-1:0] ImmOp,
    input logic ALUsrc,
    output logic [DATA_WIDTH-1:0] ALUop2
);

assign ALUop2 = ALUsrc ? ImmOp : regOp2;

endmodule

reduced_risc_v/alu/regfile.sv
module regfile #(
    parameter ADDRESS_WIDTH = 5,
    parameter DATA_WIDTH = 32
)(
    input logic clk,
    input logic WE3,
    input logic [DATA_WIDTH-1:0] WD3,
    input logic [DATA_WIDTH-1:0] Instr,
    output logic [DATA_WIDTH-1:0] RD1,
    output logic [DATA_WIDTH-1:0] RD2,
    output logic [DATA_WIDTH-1:0] a0
);

logic[4:0] rs2 = Instr[24:20];
logic[4:0] rs1 = Instr[19:15];
logic[4:0] rd = Instr[11:7];

logic [DATA_WIDTH-1:0] reg_array [2**ADDRESS_WIDTH-1:0];


always_ff @(posedge clk) begin 
    RD1 <= reg_array[rs1];
    RD2 <= reg_array[rs2];
    if(WE3 == 1) begin
        reg_array[rd] <= WD3;
    end 
    a0 <= reg_array[10];
end 

endmodule

reduced_risc_v/alu/red_top.sv
module red_top #(
    parameter DATA_WIDTH = 32 
)(
    input wire clk,
    input wire ALUsrc,
    input wire [2:0] ALUctrl,
    input wire [DATA_WIDTH-1:0] Instr,
    input wire RegWrite,
    input wire [DATA_WIDTH-1:0] ImmOp,
    output wire EQ,
    output wire [DATA_WIDTH-1:0] a0
);

wire [DATA_WIDTH-1:0] ALUout;
wire [DATA_WIDTH-1:0] ALUop1;
wire [DATA_WIDTH-1:0] ALUop2;
wire [DATA_WIDTH-1:0] regOp2;

regfile register(
    .clk(clk),
    .Instr(Instr),
    .WE3(RegWrite),
    .WD3(ALUout),
    .RD1(ALUop1),
    .RD2(regOp2),
    .a0(a0)
);

mux2 ALUMux(
    .ALUsrc(ALUsrc),
    .regOp2(regOp2),
    .ImmOp(ImmOp),
    .ALUop2(ALUop2)
);

alu ALU(
    .ALUctrl(ALUctrl),
    .ALUop1(ALUop1),
    .ALUop2(ALUop2),
    .SUM(ALUout),
    .EQ(EQ)
);

endmodule

reduced_risc_v/alu/Vred_top.vcd
$version Generated by VerilatedVcd $end
$date Mon Nov 27 12:14:33 2023 $end
$timescale 1ps $end

 $scope module TOP $end
  $var wire  3 G ALUctrl [2:0] $end
  $var wire  1 F ALUsrc $end
  $var wire  1 K EQ $end
  $var wire 32 J ImmOp [31:0] $end
  $var wire 32 H Instr [31:0] $end
  $var wire  1 I RegWrite $end
  $var wire 32 L a0 [31:0] $end
  $var wire  1 E clk $end
  $scope module red_top $end
   $var wire  3 G ALUctrl [2:0] $end
   $var wire 32 # ALUop1 [31:0] $end
   $var wire 32 N ALUop2 [31:0] $end
   $var wire 32 M ALUout [31:0] $end
   $var wire  1 F ALUsrc $end
   $var wire 32 R DATA_WIDTH [31:0] $end
   $var wire  1 K EQ $end
   $var wire 32 J ImmOp [31:0] $end
   $var wire 32 H Instr [31:0] $end
   $var wire  1 I RegWrite $end
   $var wire 32 L a0 [31:0] $end
   $var wire  1 E clk $end
   $var wire 32 $ regOp2 [31:0] $end
   $scope module ALU $end
    $var wire  3 G ALUctrl [2:0] $end
    $var wire 32 # ALUop1 [31:0] $end
    $var wire 32 N ALUop2 [31:0] $end
    $var wire 32 R DATA_WIDTH [31:0] $end
    $var wire  1 K EQ $end
    $var wire 32 M SUM [31:0] $end
   $upscope $end
   $scope module ALUMux $end
    $var wire 32 N ALUop2 [31:0] $end
    $var wire  1 F ALUsrc $end
    $var wire 32 R DATA_WIDTH [31:0] $end
    $var wire 32 J ImmOp [31:0] $end
    $var wire 32 $ regOp2 [31:0] $end
   $upscope $end
   $scope module register $end
    $var wire 32 S ADDRESS_WIDTH [31:0] $end
    $var wire 32 R DATA_WIDTH [31:0] $end
    $var wire 32 H Instr [31:0] $end
    $var wire 32 # RD1 [31:0] $end
    $var wire 32 $ RD2 [31:0] $end
    $var wire 32 M WD3 [31:0] $end
    $var wire  1 I WE3 $end
    $var wire 32 L a0 [31:0] $end
    $var wire  1 E clk $end
    $var wire  5 Q rd [4:0] $end
    $var wire 32 % reg_array[0] [31:0] $end
    $var wire 32 / reg_array[10] [31:0] $end
    $var wire 32 0 reg_array[11] [31:0] $end
    $var wire 32 1 reg_array[12] [31:0] $end
    $var wire 32 2 reg_array[13] [31:0] $end
    $var wire 32 3 reg_array[14] [31:0] $end
    $var wire 32 4 reg_array[15] [31:0] $end
    $var wire 32 5 reg_array[16] [31:0] $end
    $var wire 32 6 reg_array[17] [31:0] $end
    $var wire 32 7 reg_array[18] [31:0] $end
    $var wire 32 8 reg_array[19] [31:0] $end
    $var wire 32 & reg_array[1] [31:0] $end
    $var wire 32 9 reg_array[20] [31:0] $end
    $var wire 32 : reg_array[21] [31:0] $end
    $var wire 32 ; reg_array[22] [31:0] $end
    $var wire 32 < reg_array[23] [31:0] $end
    $var wire 32 = reg_array[24] [31:0] $end
    $var wire 32 > reg_array[25] [31:0] $end
    $var wire 32 ? reg_array[26] [31:0] $end
    $var wire 32 @ reg_array[27] [31:0] $end
    $var wire 32 A reg_array[28] [31:0] $end
    $var wire 32 B reg_array[29] [31:0] $end
    $var wire 32 ' reg_array[2] [31:0] $end
    $var wire 32 C reg_array[30] [31:0] $end
    $var wire 32 D reg_array[31] [31:0] $end
    $var wire 32 ( reg_array[3] [31:0] $end
    $var wire 32 ) reg_array[4] [31:0] $end
    $var wire 32 * reg_array[5] [31:0] $end
    $var wire 32 + reg_array[6] [31:0] $end
    $var wire 32 , reg_array[7] [31:0] $end
    $var wire 32 - reg_array[8] [31:0] $end
    $var wire 32 . reg_array[9] [31:0] $end
    $var wire  5 P rs1 [4:0] $end
    $var wire  5 O rs2 [4:0] $end
   $upscope $end
  $upscope $end
 $upscope $end
$enddefinitions $end


#0
b00000000000000000000000000000000 #
b00000000000000000000000000000000 $
b00000000000000000000000000000000 %
b00000000000000000000000000000000 &
b00000000000000000000000000000000 '
b00000000000000000000000000000000 (
b00000000000000000000000000000000 )
b00000000000000000000000000000000 *
b00000000000000000000000000000000 +
b00000000000000000000000000000000 ,
b00000000000000000000000000000000 -
b00000000000000000000000000000000 .
b00000000000000000000000000000000 /
b00000000000000000000000000000000 0
b00000000000000000000000000000000 1
b00000000000000000000000000000000 2
b00000000000000000000000000000000 3
b00000000000000000000000000000000 4
b00000000000000000000000000000000 5
b00000000000000000000000000000000 6
b00000000000000000000000000000000 7
b00000000000000000000000000000000 8
b00000000000000000000000000000000 9
b00000000000000000000000000000000 :
b00000000000000000000000000000000 ;
b00000000000000000000000000000000 <
b00000000000000000000000000000000 =
b00000000000000000000000000000000 >
b00000000000000000000000000000000 ?
b00000000000000000000000000000000 @
b00000000000000000000000000000000 A
b00000000000000000000000000000000 B
b00000000000000000000000000000000 C
b00000000000000000000000000000000 D
1E
1F
b001 G
b00000000000000000000000000000000 H
1I
b00000000000000000000000000000000 J
0K
b00000000000000000000000000000000 L
b00000000000000000000000000000000 M
b00000000000000000000000000000000 N
b00000 O
b00000 P
b00000 Q
b00000000000000000000000000100000 R
b00000000000000000000000000000101 S
#1
0E
1K
#2
1E
b00000000000100000000000000010011 H
b11111111111111111111111111111111 J
b00001 O
#3
0E
0K
b00000000000000000000000000000001 M
b11111111111111111111111111111111 N
#4
b00000000000000000000000000000001 %
1E
#5
0E
#6
b00000000000000000000000000000001 #
1E
b00000000000000000000000000000001 L
b00000000000000000000000000000010 M
#7
0E
#8
b00000000000000000000000000000010 %
1E
#9
0E
#10
b00000000000000000000000000000010 #
1E
b00000000000000000000000000000010 L
b00000000000000000000000000000011 M
#11
0E
#12
b00000000000000000000000000000011 %
1E
#13
0E
#14
b00000000000000000000000000000011 #
1E
b00000000000000000000000000000011 L
b00000000000000000000000000000100 M
#15
0E
#16
b00000000000000000000000000000100 %
1E
#17
0E
#18
b00000000000000000000000000000100 #
1E
b00000000000000000000000000000100 L
b00000000000000000000000000000101 M
#19
0E
#20
b00000000000000000000000000000101 %
1E
#21
0E
#22
b00000000000000000000000000000101 #
1E
b00000000000000000000000000000101 L
b00000000000000000000000000000110 M
#23
0E
#24
b00000000000000000000000000000110 %
1E
#25
0E
#26
b00000000000000000000000000000110 #
1E
b00000000000000000000000000000110 L
b00000000000000000000000000000111 M
#27
0E
#28
b00000000000000000000000000000111 %
1E
#29
0E
#30
b00000000000000000000000000000111 #
1E
b00000000000000000000000000000111 L
b00000000000000000000000000001000 M
#31
0E
#32
b00000000000000000000000000001000 %
1E
#33
0E
#34
b00000000000000000000000000001000 #
1E
b00000000000000000000000000001000 L
b00000000000000000000000000001001 M
#35
0E
#36
b00000000000000000000000000001001 %
1E
#37
0E
#38
b00000000000000000000000000001001 #
1E
b00000000000000000000000000001001 L
b00000000000000000000000000001010 M
#39
0E
#40
b00000000000000000000000000001010 %
1E
#41
0E
#42
b00000000000000000000000000001010 #
1E
b00000000000000000000000000001010 L
b00000000000000000000000000001011 M
#43
0E
#44
b00000000000000000000000000001011 %
1E
#45
0E
#46
b00000000000000000000000000001011 #
1E
b00000000000000000000000000001011 L
b00000000000000000000000000001100 M
#47
0E
#48
b00000000000000000000000000001100 %
1E
#49
0E
#50
b00000000000000000000000000001100 #
1E
b00000000000000000000000000001100 L
b00000000000000000000000000001101 M
#51
0E
#52
b00000000000000000000000000001101 %
1E
#53
0E
#54
b00000000000000000000000000001101 #
1E
b00000000000000000000000000001101 L
b00000000000000000000000000001110 M
#55
0E
#56
b00000000000000000000000000001110 %
1E
#57
0E
#58
b00000000000000000000000000001110 #
1E
b00000000000000000000000000001110 L
b00000000000000000000000000001111 M
#59
0E
#60
b00000000000000000000000000001111 %
1E
#61
0E
#62
b00000000000000000000000000001111 #
1E
b00000000000000000000000000001111 L
b00000000000000000000000000010000 M
#63
0E
#64
b00000000000000000000000000010000 %
1E
#65
0E
#66
b00000000000000000000000000010000 #
1E
b00000000000000000000000000010000 L
b00000000000000000000000000010001 M
#67
0E
#68
b00000000000000000000000000010001 %
1E
#69
0E
#70
b00000000000000000000000000010001 #
1E
b00000000000000000000000000010001 L
b00000000000000000000000000010010 M
#71
0E
#72
b00000000000000000000000000010010 %
1E
#73
0E
#74
b00000000000000000000000000010010 #
1E
b00000000000000000000000000010010 L
b00000000000000000000000000010011 M
#75
0E
#76
b00000000000000000000000000010011 %
1E
#77
0E
#78
b00000000000000000000000000010011 #
1E
b00000000000000000000000000010011 L
b00000000000000000000000000010100 M
#79
0E
#80
b00000000000000000000000000010100 %
1E
#81
0E
#82
b00000000000000000000000000010100 #
1E
b00000000000000000000000000010100 L
b00000000000000000000000000010101 M
#83
0E
#84
b00000000000000000000000000010101 %
1E
#85
0E
#86
b00000000000000000000000000010101 #
1E
b00000000000000000000000000010101 L
b00000000000000000000000000010110 M
#87
0E
#88
b00000000000000000000000000010110 %
1E
#89
0E
#90
b00000000000000000000000000010110 #
1E
b00000000000000000000000000010110 L
b00000000000000000000000000010111 M
#91
0E
#92
b00000000000000000000000000010111 %
1E
#93
0E
#94
b00000000000000000000000000010111 #
1E
b00000000000000000000000000010111 L
b00000000000000000000000000011000 M
#95
0E
#96
b00000000000000000000000000011000 %
1E
#97
0E
#98
b00000000000000000000000000011000 #
1E
b00000000000000000000000000011000 L
b00000000000000000000000000011001 M
#99
0E
#100
b00000000000000000000000000011001 %
1E
#101
0E
#102
b00000000000000000000000000011001 #
1E
b00000000000000000000000000011001 L
b00000000000000000000000000011010 M
#103
0E
#104
b00000000000000000000000000011010 %
1E
#105
0E
#106
b00000000000000000000000000011010 #
1E
b00000000000000000000000000011010 L
b00000000000000000000000000011011 M
#107
0E
#108
b00000000000000000000000000011011 %
1E
#109
0E
#110
b00000000000000000000000000011011 #
1E
b00000000000000000000000000011011 L
b00000000000000000000000000011100 M
#111
0E
#112
b00000000000000000000000000011100 %
1E
#113
0E
#114
b00000000000000000000000000011100 #
1E
b00000000000000000000000000011100 L
b00000000000000000000000000011101 M
#115
0E
#116
b00000000000000000000000000011101 %
1E
#117
0E
#118
b00000000000000000000000000011101 #
1E
b00000000000000000000000000011101 L
b00000000000000000000000000011110 M
#119
0E
#120
b00000000000000000000000000011110 %
1E
#121
0E
#122
b00000000000000000000000000011110 #
1E
b00000000000000000000000000011110 L
b00000000000000000000000000011111 M
#123
0E
#124
b00000000000000000000000000011111 %
1E
#125
0E
#126
b00000000000000000000000000011111 #
1E
b00000000000000000000000000011111 L
b00000000000000000000000000100000 M
#127
0E
#128
b00000000000000000000000000100000 %
1E
#129
0E
#130
b00000000000000000000000000100000 #
1E
b00000000000000000000000000100000 L
b00000000000000000000000000100001 M
#131
0E
#132
b00000000000000000000000000100001 %
1E
#133
0E
#134
b00000000000000000000000000100001 #
1E
b00000000000000000000000000100001 L
b00000000000000000000000000100010 M
#135
0E
#136
b00000000000000000000000000100010 %
1E
#137
0E
#138
b00000000000000000000000000100010 #
1E
b00000000000000000000000000100010 L
b00000000000000000000000000100011 M
#139
0E
#140
b00000000000000000000000000100011 %
1E
#141
0E
#142
b00000000000000000000000000100011 #
1E
b00000000000000000000000000100011 L
b00000000000000000000000000100100 M
#143
0E
#144
b00000000000000000000000000100100 %
1E
#145
0E
#146
b00000000000000000000000000100100 #
1E
b00000000000000000000000000100100 L
b00000000000000000000000000100101 M
#147
0E
#148
b00000000000000000000000000100101 %
1E
#149
0E
#150
b00000000000000000000000000100101 #
1E
b00000000000000000000000000100101 L
b00000000000000000000000000100110 M
#151
0E
#152
b00000000000000000000000000100110 %
1E
#153
0E
#154
b00000000000000000000000000100110 #
1E
b00000000000000000000000000100110 L
b00000000000000000000000000100111 M
#155
0E
#156
b00000000000000000000000000100111 %
1E
#157
0E
#158
b00000000000000000000000000100111 #
1E
b00000000000000000000000000100111 L
b00000000000000000000000000101000 M
#159
0E
#160
b00000000000000000000000000101000 %
1E
#161
0E
#162
b00000000000000000000000000101000 #
1E
b00000000000000000000000000101000 L
b00000000000000000000000000101001 M
#163
0E
#164
b00000000000000000000000000101001 %
1E
#165
0E
#166
b00000000000000000000000000101001 #
1E
b00000000000000000000000000101001 L
b00000000000000000000000000101010 M
#167
0E
#168
b00000000000000000000000000101010 %
1E
#169
0E
#170
b00000000000000000000000000101010 #
1E
b00000000000000000000000000101010 L
b00000000000000000000000000101011 M
#171
0E
#172
b00000000000000000000000000101011 %
1E
#173
0E
#174
b00000000000000000000000000101011 #
1E
b00000000000000000000000000101011 L
b00000000000000000000000000101100 M
#175
0E
#176
b00000000000000000000000000101100 %
1E
#177
0E
#178
b00000000000000000000000000101100 #
1E
b00000000000000000000000000101100 L
b00000000000000000000000000101101 M
#179
0E
#180
b00000000000000000000000000101101 %
1E
#181
0E
#182
b00000000000000000000000000101101 #
1E
b00000000000000000000000000101101 L
b00000000000000000000000000101110 M
#183
0E
#184
b00000000000000000000000000101110 %
1E
#185
0E
#186
b00000000000000000000000000101110 #
1E
b00000000000000000000000000101110 L
b00000000000000000000000000101111 M
#187
0E
#188
b00000000000000000000000000101111 %
1E
#189
0E
#190
b00000000000000000000000000101111 #
1E
b00000000000000000000000000101111 L
b00000000000000000000000000110000 M
#191
0E
#192
b00000000000000000000000000110000 %
1E
#193
0E
#194
b00000000000000000000000000110000 #
1E
b00000000000000000000000000110000 L
b00000000000000000000000000110001 M
#195
0E
#196
b00000000000000000000000000110001 %
1E
#197
0E
#198
b00000000000000000000000000110001 #
1E
b00000000000000000000000000110001 L
b00000000000000000000000000110010 M
#199
0E
#200
b00000000000000000000000000110010 %
1E
#201
0E
#202
b00000000000000000000000000110010 #
1E
b00000000000000000000000000110010 L
b00000000000000000000000000110011 M
#203
0E
#204
b00000000000000000000000000110011 %
1E
#205
0E
#206
b00000000000000000000000000110011 #
1E
b00000000000000000000000000110011 L
b00000000000000000000000000110100 M
#207
0E
#208
b00000000000000000000000000110100 %
1E
#209
0E
#210
b00000000000000000000000000110100 #
1E
b00000000000000000000000000110100 L
b00000000000000000000000000110101 M
#211
0E
#212
b00000000000000000000000000110101 %
1E
#213
0E
#214
b00000000000000000000000000110101 #
1E
b00000000000000000000000000110101 L
b00000000000000000000000000110110 M
#215
0E
#216
b00000000000000000000000000110110 %
1E
#217
0E
#218
b00000000000000000000000000110110 #
1E
b00000000000000000000000000110110 L
b00000000000000000000000000110111 M
#219
0E
#220
b00000000000000000000000000110111 %
1E
#221
0E
#222
b00000000000000000000000000110111 #
1E
b00000000000000000000000000110111 L
b00000000000000000000000000111000 M
#223
0E
#224
b00000000000000000000000000111000 %
1E
#225
0E
#226
b00000000000000000000000000111000 #
1E
b00000000000000000000000000111000 L
b00000000000000000000000000111001 M
#227
0E
#228
b00000000000000000000000000111001 %
1E
#229
0E
#230
b00000000000000000000000000111001 #
1E
b00000000000000000000000000111001 L
b00000000000000000000000000111010 M
#231
0E
#232
b00000000000000000000000000111010 %
1E
#233
0E
#234
b00000000000000000000000000111010 #
1E
b00000000000000000000000000111010 L
b00000000000000000000000000111011 M
#235
0E
#236
b00000000000000000000000000111011 %
1E
#237
0E
#238
b00000000000000000000000000111011 #
1E
b00000000000000000000000000111011 L
b00000000000000000000000000111100 M
#239
0E
#240
b00000000000000000000000000111100 %
1E
#241
0E
#242
b00000000000000000000000000111100 #
1E
b00000000000000000000000000111100 L
b00000000000000000000000000111101 M
#243
0E
#244
b00000000000000000000000000111101 %
1E
#245
0E
#246
b00000000000000000000000000111101 #
1E
b00000000000000000000000000111101 L
b00000000000000000000000000111110 M
#247
0E
#248
b00000000000000000000000000111110 %
1E
#249
0E
#250
b00000000000000000000000000111110 #
1E
b00000000000000000000000000111110 L
b00000000000000000000000000111111 M
#251
0E
#252
b00000000000000000000000000111111 %
1E
#253
0E
#254
b00000000000000000000000000111111 #
1E
b00000000000000000000000000111111 L
b00000000000000000000000001000000 M
#255
0E
#256
b00000000000000000000000001000000 %
1E
#257
0E
#258
b00000000000000000000000001000000 #
1E
b00000000000000000000000001000000 L
b00000000000000000000000001000001 M
#259
0E
#260
b00000000000000000000000001000001 %
1E
#261
0E
#262
b00000000000000000000000001000001 #
1E
b00000000000000000000000001000001 L
b00000000000000000000000001000010 M
#263
0E
#264
b00000000000000000000000001000010 %
1E
#265
0E
#266
b00000000000000000000000001000010 #
1E
b00000000000000000000000001000010 L
b00000000000000000000000001000011 M
#267
0E
#268
b00000000000000000000000001000011 %
1E
#269
0E
#270
b00000000000000000000000001000011 #
1E
b00000000000000000000000001000011 L
b00000000000000000000000001000100 M
#271
0E
#272
b00000000000000000000000001000100 %
1E
#273
0E
#274
b00000000000000000000000001000100 #
1E
b00000000000000000000000001000100 L
b00000000000000000000000001000101 M
#275
0E
#276
b00000000000000000000000001000101 %
1E
#277
0E
#278
b00000000000000000000000001000101 #
1E
b00000000000000000000000001000101 L
b00000000000000000000000001000110 M
#279
0E
#280
b00000000000000000000000001000110 %
1E
#281
0E
#282
b00000000000000000000000001000110 #
1E
b00000000000000000000000001000110 L
b00000000000000000000000001000111 M
#283
0E
#284
b00000000000000000000000001000111 %
1E
#285
0E
#286
b00000000000000000000000001000111 #
1E
b00000000000000000000000001000111 L
b00000000000000000000000001001000 M
#287
0E
#288
b00000000000000000000000001001000 %
1E
#289
0E
#290
b00000000000000000000000001001000 #
1E
b00000000000000000000000001001000 L
b00000000000000000000000001001001 M
#291
0E
#292
b00000000000000000000000001001001 %
1E
#293
0E
#294
b00000000000000000000000001001001 #
1E
b00000000000000000000000001001001 L
b00000000000000000000000001001010 M
#295
0E
#296
b00000000000000000000000001001010 %
1E
#297
0E
#298
b00000000000000000000000001001010 #
1E
b00000000000000000000000001001010 L
b00000000000000000000000001001011 M
#299
0E
#300
b00000000000000000000000001001011 %
1E
#301
0E
#302
b00000000000000000000000001001011 #
1E
b00000000000000000000000001001011 L
b00000000000000000000000001001100 M
#303
0E
#304
b00000000000000000000000001001100 %
1E
#305
0E
#306
b00000000000000000000000001001100 #
1E
b00000000000000000000000001001100 L
b00000000000000000000000001001101 M
#307
0E
#308
b00000000000000000000000001001101 %
1E
#309
0E
#310
b00000000000000000000000001001101 #
1E
b00000000000000000000000001001101 L
b00000000000000000000000001001110 M
#311
0E
#312
b00000000000000000000000001001110 %
1E
#313
0E
#314
b00000000000000000000000001001110 #
1E
b00000000000000000000000001001110 L
b00000000000000000000000001001111 M
#315
0E
#316
b00000000000000000000000001001111 %
1E
#317
0E
#318
b00000000000000000000000001001111 #
1E
b00000000000000000000000001001111 L
b00000000000000000000000001010000 M
#319
0E
#320
b00000000000000000000000001010000 %
1E
#321
0E
#322
b00000000000000000000000001010000 #
1E
b00000000000000000000000001010000 L
b00000000000000000000000001010001 M
#323
0E
#324
b00000000000000000000000001010001 %
1E
#325
0E
#326
b00000000000000000000000001010001 #
1E
b00000000000000000000000001010001 L
b00000000000000000000000001010010 M
#327
0E
#328
b00000000000000000000000001010010 %
1E
#329
0E
#330
b00000000000000000000000001010010 #
1E
b00000000000000000000000001010010 L
b00000000000000000000000001010011 M
#331
0E
#332
b00000000000000000000000001010011 %
1E
#333
0E
#334
b00000000000000000000000001010011 #
1E
b00000000000000000000000001010011 L
b00000000000000000000000001010100 M
#335
0E
#336
b00000000000000000000000001010100 %
1E
#337
0E
#338
b00000000000000000000000001010100 #
1E
b00000000000000000000000001010100 L
b00000000000000000000000001010101 M
#339
0E
#340
b00000000000000000000000001010101 %
1E
#341
0E
#342
b00000000000000000000000001010101 #
1E
b00000000000000000000000001010101 L
b00000000000000000000000001010110 M
#343
0E
#344
b00000000000000000000000001010110 %
1E
#345
0E
#346
b00000000000000000000000001010110 #
1E
b00000000000000000000000001010110 L
b00000000000000000000000001010111 M
#347
0E
#348
b00000000000000000000000001010111 %
1E
#349
0E
#350
b00000000000000000000000001010111 #
1E
b00000000000000000000000001010111 L
b00000000000000000000000001011000 M
#351
0E
#352
b00000000000000000000000001011000 %
1E
#353
0E
#354
b00000000000000000000000001011000 #
1E
b00000000000000000000000001011000 L
b00000000000000000000000001011001 M
#355
0E
#356
b00000000000000000000000001011001 %
1E
#357
0E
#358
b00000000000000000000000001011001 #
1E
b00000000000000000000000001011001 L
b00000000000000000000000001011010 M
#359
0E
#360
b00000000000000000000000001011010 %
1E
#361
0E
#362
b00000000000000000000000001011010 #
1E
b00000000000000000000000001011010 L
b00000000000000000000000001011011 M
#363
0E
#364
b00000000000000000000000001011011 %
1E
#365
0E
#366
b00000000000000000000000001011011 #
1E
b00000000000000000000000001011011 L
b00000000000000000000000001011100 M
#367
0E
#368
b00000000000000000000000001011100 %
1E
#369
0E
#370
b00000000000000000000000001011100 #
1E
b00000000000000000000000001011100 L
b00000000000000000000000001011101 M
#371
0E
#372
b00000000000000000000000001011101 %
1E
#373
0E
#374
b00000000000000000000000001011101 #
1E
b00000000000000000000000001011101 L
b00000000000000000000000001011110 M
#375
0E
#376
b00000000000000000000000001011110 %
1E
#377
0E
#378
b00000000000000000000000001011110 #
1E
b00000000000000000000000001011110 L
b00000000000000000000000001011111 M
#379
0E
#380
b00000000000000000000000001011111 %
1E
#381
0E
#382
b00000000000000000000000001011111 #
1E
b00000000000000000000000001011111 L
b00000000000000000000000001100000 M
#383
0E
#384
b00000000000000000000000001100000 %
1E
#385
0E
#386
b00000000000000000000000001100000 #
1E
b00000000000000000000000001100000 L
b00000000000000000000000001100001 M
#387
0E
#388
b00000000000000000000000001100001 %
1E
#389
0E
#390
b00000000000000000000000001100001 #
1E
b00000000000000000000000001100001 L
b00000000000000000000000001100010 M
#391
0E
#392
b00000000000000000000000001100010 %
1E
#393
0E
#394
b00000000000000000000000001100010 #
1E
b00000000000000000000000001100010 L
b00000000000000000000000001100011 M
#395
0E
#396
b00000000000000000000000001100011 %
1E
#397
0E
#398
b00000000000000000000000001100011 #
1E
b00000000000000000000000001100011 L
b00000000000000000000000001100100 M
#399
0E
#400
b00000000000000000000000001100100 %
1E
#401
0E
#402
b00000000000000000000000001100100 #
1E
b00000000000000000000000001100100 L
b00000000000000000000000001100101 M
#403
0E
#404
b00000000000000000000000001100101 %
1E
#405
0E
#406
b00000000000000000000000001100101 #
1E
b00000000000000000000000001100101 L
b00000000000000000000000001100110 M
#407
0E
#408
b00000000000000000000000001100110 %
1E
#409
0E
#410
b00000000000000000000000001100110 #
1E
b00000000000000000000000001100110 L
b00000000000000000000000001100111 M
#411
0E
#412
b00000000000000000000000001100111 %
1E
#413
0E
#414
b00000000000000000000000001100111 #
1E
b00000000000000000000000001100111 L
b00000000000000000000000001101000 M
#415
0E
#416
b00000000000000000000000001101000 %
1E
#417
0E
#418
b00000000000000000000000001101000 #
1E
b00000000000000000000000001101000 L
b00000000000000000000000001101001 M
#419
0E
#420
b00000000000000000000000001101001 %
1E
#421
0E
#422
b00000000000000000000000001101001 #
1E
b00000000000000000000000001101001 L
b00000000000000000000000001101010 M
#423
0E
#424
b00000000000000000000000001101010 %
1E
#425
0E
#426
b00000000000000000000000001101010 #
1E
b00000000000000000000000001101010 L
b00000000000000000000000001101011 M
#427
0E
#428
b00000000000000000000000001101011 %
1E
#429
0E
#430
b00000000000000000000000001101011 #
1E
b00000000000000000000000001101011 L
b00000000000000000000000001101100 M
#431
0E
#432
b00000000000000000000000001101100 %
1E
#433
0E
#434
b00000000000000000000000001101100 #
1E
b00000000000000000000000001101100 L
b00000000000000000000000001101101 M
#435
0E
#436
b00000000000000000000000001101101 %
1E
#437
0E
#438
b00000000000000000000000001101101 #
1E
b00000000000000000000000001101101 L
b00000000000000000000000001101110 M
#439
0E
#440
b00000000000000000000000001101110 %
1E
#441
0E
#442
b00000000000000000000000001101110 #
1E
b00000000000000000000000001101110 L
b00000000000000000000000001101111 M
#443
0E
#444
b00000000000000000000000001101111 %
1E
#445
0E
#446
b00000000000000000000000001101111 #
1E
b00000000000000000000000001101111 L
b00000000000000000000000001110000 M
#447
0E
#448
b00000000000000000000000001110000 %
1E
#449
0E
#450
b00000000000000000000000001110000 #
1E
b00000000000000000000000001110000 L
b00000000000000000000000001110001 M
#451
0E
#452
b00000000000000000000000001110001 %
1E
#453
0E
#454
b00000000000000000000000001110001 #
1E
b00000000000000000000000001110001 L
b00000000000000000000000001110010 M
#455
0E
#456
b00000000000000000000000001110010 %
1E
#457
0E
#458
b00000000000000000000000001110010 #
1E
b00000000000000000000000001110010 L
b00000000000000000000000001110011 M
#459
0E
#460
b00000000000000000000000001110011 %
1E
#461
0E
#462
b00000000000000000000000001110011 #
1E
b00000000000000000000000001110011 L
b00000000000000000000000001110100 M
#463
0E
#464
b00000000000000000000000001110100 %
1E
#465
0E
#466
b00000000000000000000000001110100 #
1E
b00000000000000000000000001110100 L
b00000000000000000000000001110101 M
#467
0E
#468
b00000000000000000000000001110101 %
1E
#469
0E
#470
b00000000000000000000000001110101 #
1E
b00000000000000000000000001110101 L
b00000000000000000000000001110110 M
#471
0E
#472
b00000000000000000000000001110110 %
1E
#473
0E
#474
b00000000000000000000000001110110 #
1E
b00000000000000000000000001110110 L
b00000000000000000000000001110111 M
#475
0E
#476
b00000000000000000000000001110111 %
1E
#477
0E
#478
b00000000000000000000000001110111 #
1E
b00000000000000000000000001110111 L
b00000000000000000000000001111000 M
#479
0E
#480
b00000000000000000000000001111000 %
1E
#481
0E
#482
b00000000000000000000000001111000 #
1E
b00000000000000000000000001111000 L
b00000000000000000000000001111001 M
#483
0E
#484
b00000000000000000000000001111001 %
1E
#485
0E
#486
b00000000000000000000000001111001 #
1E
b00000000000000000000000001111001 L
b00000000000000000000000001111010 M
#487
0E
#488
b00000000000000000000000001111010 %
1E
#489
0E
#490
b00000000000000000000000001111010 #
1E
b00000000000000000000000001111010 L
b00000000000000000000000001111011 M
#491
0E
#492
b00000000000000000000000001111011 %
1E
#493
0E
#494
b00000000000000000000000001111011 #
1E
b00000000000000000000000001111011 L
b00000000000000000000000001111100 M
#495
0E
#496
b00000000000000000000000001111100 %
1E
#497
0E
#498
b00000000000000000000000001111100 #
1E
b00000000000000000000000001111100 L
b00000000000000000000000001111101 M
#499
0E
#500
b00000000000000000000000001111101 %
1E
#501
0E
#502
b00000000000000000000000001111101 #
1E
b00000000000000000000000001111101 L
b00000000000000000000000001111110 M
#503
0E
#504
b00000000000000000000000001111110 %
1E
#505
0E
#506
b00000000000000000000000001111110 #
1E
b00000000000000000000000001111110 L
b00000000000000000000000001111111 M
#507
0E
#508
b00000000000000000000000001111111 %
1E
#509
0E
#510
b00000000000000000000000001111111 #
1E
b00000000000000000000000001111111 L
b00000000000000000000000010000000 M
#511
0E
#512
b00000000000000000000000010000000 %
1E
#513
0E
#514
b00000000000000000000000010000000 #
1E
b00000000000000000000000010000000 L
b00000000000000000000000010000001 M
#515
0E
#516
b00000000000000000000000010000001 %
1E
#517
0E
#518
b00000000000000000000000010000001 #
1E
b00000000000000000000000010000001 L
b00000000000000000000000010000010 M
#519
0E
#520
b00000000000000000000000010000010 %
1E
#521
0E
#522
b00000000000000000000000010000010 #
1E
b00000000000000000000000010000010 L
b00000000000000000000000010000011 M
#523
0E
#524
b00000000000000000000000010000011 %
1E
