reduced_risc_v/cpu_test_old/alu.sv
module alu #(
    parameter DATA_WIDTH = 32
)(
    input logic [2:0] ALUctrl,
    input logic [DATA_WIDTH-1:0] ALUop1,
    input logic [DATA_WIDTH-1:0] ALUop2,
    output logic [DATA_WIDTH-1:0] SUM,
    output logic [2:0] aluctrl2,
    output logic EQ
);

always_comb begin

    aluctrl2 = ALUctrl;
    case (ALUctrl)
    3'b000: SUM = ALUop1 + ALUop2;
    3'b001: SUM = ALUop1 - ALUop2;
    3'b010: SUM = ALUop1 & ALUop2;
    3'b011: SUM = ALUop1 | ALUop2;
    3'b100: SUM = ALUop1 ^ ALUop2;

    default: SUM = 0;

    endcase 

    assign EQ = (ALUop1 == ALUop2);

end 

endmodule

reduced_risc_v/cpu_test_old/mux2.sv
module mux2 #(
    parameter DATA_WIDTH = 32
)(
    input logic [DATA_WIDTH-1:0] regOp2,
    input logic [DATA_WIDTH-1:0] ImmOp,
    input logic ALUsrc,
    output logic [DATA_WIDTH-1:0] ALUop2
);

assign ALUop2 = ALUsrc ? ImmOp : regOp2;

endmodule

reduced_risc_v/cpu_test_old/regfile.sv
module regfile #(
    parameter ADDRESS_WIDTH = 5,
    parameter DATA_WIDTH = 32
)(
    input logic clk,
    input logic WE3,
    input logic [DATA_WIDTH-1:0] WD3,
    input logic [DATA_WIDTH-1:0] Instr,
    output logic [DATA_WIDTH-1:0] RD1,
    output logic [DATA_WIDTH-1:0] RD2,
    output logic [DATA_WIDTH-1:0] a0
);

logic[4:0] rs2 = Instr[24:20];
logic[4:0] rs1 = Instr[19:15];
logic[4:0] rd = Instr[11:7];

logic [DATA_WIDTH-1:0] reg_array [2**ADDRESS_WIDTH-1:0];

assign RD1 = reg_array[rs1];
assign RD2 = reg_array[rs2];

always_ff @(posedge clk) begin 
    if(WE3 == 1) begin
        reg_array[rd] <= WD3;
    end 
end 

assign a0 = reg_array[10];



endmodule

reduced_risc_v/alu/red_top.sv
module red_top #(
    parameter DATA_WIDTH = 32 
)(
    input wire clk,
    input wire ALUsrc,
    input wire [2:0] ALUctrl,
    input wire [DATA_WIDTH-1:0] Instr,
    input wire RegWrite,
    input wire [DATA_WIDTH-1:0] ImmOp,
    output wire EQ,
    output wire [DATA_WIDTH-1:0] a0
);

wire [DATA_WIDTH-1:0] ALUout;
wire [DATA_WIDTH-1:0] ALUop1;
wire [DATA_WIDTH-1:0] ALUop2;
wire [DATA_WIDTH-1:0] regOp2;

regfile register(
    .clk(clk),
    .Instr(Instr),
    .WE3(RegWrite),
    .WD3(ALUout),
    .RD1(ALUop1),
    .RD2(regOp2),
    .a0(a0)
);

mux2 ALUMux(
    .ALUsrc(ALUsrc),
    .regOp2(regOp2),
    .ImmOp(ImmOp),
    .ALUop2(ALUop2)
);

alu ALU(
    .ALUctrl(ALUctrl),
    .ALUop1(ALUop1),
    .ALUop2(ALUop2),
    .SUM(ALUout),
    .EQ(EQ)
);

endmodule

reduced_risc_v/cpu_test_old/SignExtend.sv
module SignExtend #(
    parameter DATA_WIDTH = 32
)(
    input logic [DATA_WIDTH-1:0]        instr,
    input logic [1:0]                   ImmSrc,
    output logic [DATA_WIDTH-1:0]        ImmOp
);

always_comb 
    case (ImmSrc)
    2'b01: ImmOp = {{DATA_WIDTH-12{instr[31]}}, instr[31:20]}; //I instruction
                    //20                        1           6              4        1      = 32 bits          
    2'b11: ImmOp = {{DATA_WIDTH-12{instr[31]}}, instr[7], instr[30:25], instr[11:8], 1'b0}; //B instructions
        
    default ImmOp = 32'b0;
    
    endcase 
endmodule

reduced_risc_v/cpu_test_old/InstrMem.sv
module InstrMem #(
    parameter ADDRESS_WIDTH = 8,
    DATA_WIDTH = 32
)(
    input logic [DATA_WIDTH-1:0] addr,

    output logic [DATA_WIDTH-1:0]   dout
);

logic [DATA_WIDTH-1:0] rom_array [2**ADDRESS_WIDTH-1:0];

initial begin
        $display("Loading rom.");
        $readmemh("machinecode.mem", rom_array);
end;

always_comb 
dout = rom_array[{addr/4}];


endmodule

reduced_risc_v/cpu_test_old/ControlUnit.sv
module ControlUnit #(
    parameter DATA_WIDTH = 32
)(
     input logic                         EQ,
     input logic [DATA_WIDTH-1:0]        instr,
          output logic [DATA_WIDTH-1:0]        instr2,

     output logic                        RegWrite,
     output logic [2:0]                  ALUctrl,
     output logic                        ALUsrc,
     output logic [1:0]                 ImmSrc, 
     output logic                        PCsrc
     //output logic [DATA_WIDTH-1:0]       Instruction2
);
    //for ImmSrc
    //R => 00
    //I => 01
    //S => 10
    //B => 11

    logic [6:0] opcode = instr[6:0];
    
    always_comb  begin

    instr2 = instr;
    case (opcode)
    7'b0010011: begin //addi instruction
        RegWrite = 1;
        ALUctrl = 3'b000;
        ALUsrc = 1;
        ImmSrc = 2'b01;
        PCsrc = 0;
    end
    7'b1100011: begin //bne instruction
        RegWrite = 0;
        ALUctrl = 3'b000;
        ALUsrc = 0;
        ImmSrc = 2'b11;
        PCsrc = !EQ;
    end
        default begin //just in case we have something else
        RegWrite = 1;
        ALUctrl = 3'b000;
        ALUsrc = 1;
        ImmSrc = 2'b00;
        PCsrc = 0;
    end
    endcase 
    end
endmodule

reduced_risc_v/cpu_test_old/green.sv
module green #(
    parameter   //ADDRESS_WIDTH = 8,
                DATA_WIDTH = 32
)(
     input logic [DATA_WIDTH-1:0]     PC, //8b
     input logic                        EQ, //1b
     output logic [DATA_WIDTH-1:0]       instr,//32b

     output logic                        RegWrite, //1b
     output logic [2:0]                  ALUctrl, //3b
     output logic                        ALUsrc, //1 bit
     output logic                        PCsrc, //1 bit
     output logic [DATA_WIDTH-1:0]        ImmOp //32 bits
     //output logic [DATA_WIDTH-1:0]       Instruction2


);

    logic [1:0]                        ImmSrc;

ControlUnit MyControlUnit(
    .EQ(EQ),
    .instr(instr),
    .RegWrite(RegWrite),
    .ALUctrl(ALUctrl),
    .ALUsrc(ALUsrc),
    .ImmSrc(ImmSrc),
    .PCsrc(PCsrc)

);

InstrMem MyInstrMem(
    .addr(PC),
    .dout(instr)
);

SignExtend MySignExtend(
    .instr(instr),
    .ImmSrc(ImmSrc),
    .ImmOp(ImmOp)
);

endmodule

reduced_risc_v/cpu_test_old/pc_reg.sv
module pc_reg #(
    parameter WIDTH = 32
)(
    input logic clk, 
    input logic rst, 
    input logic [WIDTH-1:0] next_PC,
    output logic [WIDTH-1:0] pc,

    output logic [WIDTH-1:0] another_pc
);

always_ff @ (posedge clk)
begin
    if (rst)
        pc <= {WIDTH{1'b0}};
    else
        pc <= next_PC;

    another_pc <= next_PC;
end

endmodule

reduced_risc_v/cpu_test_old/pc_mux.sv
module pc_mux #(
    parameter WIDTH = 32
)(
    input logic PCsrc,
    input logic [WIDTH-1:0] pc ,
    input logic [WIDTH-1:0] ImmOp,
    output logic [WIDTH-1:0] next_PC
);

    assign next_PC = PCsrc ? pc + ImmOp : pc + 32'd4;

endmodule

reduced_risc_v/cpu_test_old/pc_top.sv
module pc_top #(
    parameter   WIDTH = 8
)(
    // interface signals
    input   logic                       clk,        // clock
    input   logic                       rst,        // reset        
    input   logic [WIDTH-1:0]           ImmOp,     
    input   logic                       PCsrc,
    output logic [WIDTH-1:0]            pc_out
);

logic [WIDTH-1:0]   next_PC, pc;    // interconnect wire

pc_mux pc_mux(
    //.clk (clk),
    .PCsrc (PCsrc),
    .ImmOp (ImmOp),
    .next_PC (next_PC),
    .pc (pc)
);

pc_reg pc_reg(
    .clk (clk),
    .rst (rst),
    .next_PC (next_PC),
    .pc (pc),
    .another_pc(pc_out)
);

endmodule

reduced_risc_v/cpu_test_old/cpu.sv
module cpu #(

    parameter DATA_WIDTH = 32
    //ADDRESS_WIDTH = 8

)(

    input logic                        clk,
    input logic                        rst,
    output logic [DATA_WIDTH-1:0]      a0


);

    //output internal logic for "green" module 
    logic   RegWrite;
    logic   [2:0] ALUctrl;
    logic   ALUsrc;
    //logic   ImmSrc;
    logic   PCsrc;
    logic   [DATA_WIDTH-1:0] ImmOp;
    logic   [DATA_WIDTH-1:0] Instr;

    //output internal logic for "red" module 
    logic EQ;

    //output internal logic for "blue" module
    logic [DATA_WIDTH-1:0] PC;

    //and then we would specify the "submodules here"   
        //green
        //blue
        //red
    //we can change the names 

pc_top Myblue(
    .clk(clk),
    .rst(rst),
    .pc_out(PC),
    .PCsrc(PCsrc),
    .ImmOp(ImmOp)
    );

green Mygreen(
    .EQ(EQ),
    .RegWrite(RegWrite),
    .ALUctrl(ALUctrl),
    .ALUsrc(ALUsrc),
    //.ImmSrc(ImmSrc),
    .PCsrc(PCsrc),
    .ImmOp(ImmOp),
    .PC(PC),
    .instr(Instr)
);

red_top Myred(
    .clk(clk),
    .a0(a0),
    .Instr(Instr),//we pass the whole Instruction, and then we separate inside red
    .RegWrite(RegWrite),
    .EQ(EQ),
    .ALUctrl(ALUctrl),
    .ALUsrc(ALUsrc),
    .ImmOp(ImmOp)
);
    
endmodule

reduced_risc_v/cpu_test_old/cpu.vcd
$version Generated by VerilatedVcd $end
$date Thu Nov 30 13:31:04 2023 $end
$timescale 1ps $end

 $scope module TOP $end
  $var wire 32 ^ a0 [31:0] $end
  $var wire  1 \ clk $end
  $var wire  1 ] rst $end
  $scope module cpu $end
   $var wire  3 ` ALUctrl [2:0] $end
   $var wire  1 # ALUsrc $end
   $var wire 32 _ DATA_WIDTH [31:0] $end
   $var wire  1 ' EQ $end
   $var wire 32 % ImmOp [31:0] $end
   $var wire 32 & Instr [31:0] $end
   $var wire 32 ( PC [31:0] $end
   $var wire  1 $ PCsrc $end
   $var wire  1 # RegWrite $end
   $var wire 32 ^ a0 [31:0] $end
   $var wire  1 \ clk $end
   $var wire  1 ] rst $end
   $scope module Myblue $end
    $var wire  8 ) ImmOp [7:0] $end
    $var wire  1 $ PCsrc $end
    $var wire 32 a WIDTH [31:0] $end
    $var wire  1 \ clk $end
    $var wire  8 + next_PC [7:0] $end
    $var wire  8 , pc [7:0] $end
    $var wire  8 * pc_out [7:0] $end
    $var wire  1 ] rst $end
    $scope module pc_mux $end
     $var wire 32 . ImmOp [31:0] $end
     $var wire  1 $ PCsrc $end
     $var wire 32 _ WIDTH [31:0] $end
     $var wire 32 / next_PC [31:0] $end
     $var wire 32 - pc [31:0] $end
    $upscope $end
    $scope module pc_reg $end
     $var wire 32 _ WIDTH [31:0] $end
     $var wire 32 2 another_pc [31:0] $end
     $var wire  1 \ clk $end
     $var wire 32 0 next_PC [31:0] $end
     $var wire 32 1 pc [31:0] $end
     $var wire  1 ] rst $end
    $upscope $end
   $upscope $end
   $scope module Mygreen $end
    $var wire  3 ` ALUctrl [2:0] $end
    $var wire  1 # ALUsrc $end
    $var wire 32 _ DATA_WIDTH [31:0] $end
    $var wire  1 ' EQ $end
    $var wire 32 % ImmOp [31:0] $end
    $var wire  2 3 ImmSrc [1:0] $end
    $var wire 32 ( PC [31:0] $end
    $var wire  1 $ PCsrc $end
    $var wire  1 # RegWrite $end
    $var wire 32 & instr [31:0] $end
    $scope module MyControlUnit $end
     $var wire  3 ` ALUctrl [2:0] $end
     $var wire  1 # ALUsrc $end
     $var wire 32 _ DATA_WIDTH [31:0] $end
     $var wire  1 ' EQ $end
     $var wire  2 3 ImmSrc [1:0] $end
     $var wire  1 $ PCsrc $end
     $var wire  1 # RegWrite $end
     $var wire 32 & instr [31:0] $end
     $var wire 32 & instr2 [31:0] $end
     $var wire  7 4 opcode [6:0] $end
    $upscope $end
    $scope module MyInstrMem $end
     $var wire 32 a ADDRESS_WIDTH [31:0] $end
     $var wire 32 _ DATA_WIDTH [31:0] $end
     $var wire 32 ( addr [31:0] $end
     $var wire 32 & dout [31:0] $end
    $upscope $end
    $scope module MySignExtend $end
     $var wire 32 _ DATA_WIDTH [31:0] $end
     $var wire 32 % ImmOp [31:0] $end
     $var wire  2 3 ImmSrc [1:0] $end
     $var wire 32 & instr [31:0] $end
    $upscope $end
   $upscope $end
   $scope module Myred $end
    $var wire  3 ` ALUctrl [2:0] $end
    $var wire 32 6 ALUop1 [31:0] $end
    $var wire 32 7 ALUop2 [31:0] $end
    $var wire 32 5 ALUout [31:0] $end
    $var wire  1 # ALUsrc $end
    $var wire 32 _ DATA_WIDTH [31:0] $end
    $var wire  1 ' EQ $end
    $var wire 32 % ImmOp [31:0] $end
    $var wire 32 & Instr [31:0] $end
    $var wire  1 # RegWrite $end
    $var wire 32 ^ a0 [31:0] $end
    $var wire  1 \ clk $end
    $var wire 32 8 regOp2 [31:0] $end
    $scope module ALU $end
     $var wire  3 ` ALUctrl [2:0] $end
     $var wire 32 6 ALUop1 [31:0] $end
     $var wire 32 7 ALUop2 [31:0] $end
     $var wire 32 _ DATA_WIDTH [31:0] $end
     $var wire  1 ' EQ $end
     $var wire 32 5 SUM [31:0] $end
     $var wire  3 ` aluctrl2 [2:0] $end
    $upscope $end
    $scope module ALUMux $end
     $var wire 32 7 ALUop2 [31:0] $end
     $var wire  1 # ALUsrc $end
     $var wire 32 _ DATA_WIDTH [31:0] $end
     $var wire 32 % ImmOp [31:0] $end
     $var wire 32 8 regOp2 [31:0] $end
    $upscope $end
    $scope module register $end
     $var wire 32 b ADDRESS_WIDTH [31:0] $end
     $var wire 32 _ DATA_WIDTH [31:0] $end
     $var wire 32 & Instr [31:0] $end
     $var wire 32 6 RD1 [31:0] $end
     $var wire 32 8 RD2 [31:0] $end
     $var wire 32 5 WD3 [31:0] $end
     $var wire  1 # WE3 $end
     $var wire 32 ^ a0 [31:0] $end
     $var wire  1 \ clk $end
     $var wire  5 ; rd [4:0] $end
     $var wire 32 < reg_array[0] [31:0] $end
     $var wire 32 F reg_array[10] [31:0] $end
     $var wire 32 G reg_array[11] [31:0] $end
     $var wire 32 H reg_array[12] [31:0] $end
     $var wire 32 I reg_array[13] [31:0] $end
     $var wire 32 J reg_array[14] [31:0] $end
     $var wire 32 K reg_array[15] [31:0] $end
     $var wire 32 L reg_array[16] [31:0] $end
     $var wire 32 M reg_array[17] [31:0] $end
     $var wire 32 N reg_array[18] [31:0] $end
     $var wire 32 O reg_array[19] [31:0] $end
     $var wire 32 = reg_array[1] [31:0] $end
     $var wire 32 P reg_array[20] [31:0] $end
     $var wire 32 Q reg_array[21] [31:0] $end
     $var wire 32 R reg_array[22] [31:0] $end
     $var wire 32 S reg_array[23] [31:0] $end
     $var wire 32 T reg_array[24] [31:0] $end
     $var wire 32 U reg_array[25] [31:0] $end
     $var wire 32 V reg_array[26] [31:0] $end
     $var wire 32 W reg_array[27] [31:0] $end
     $var wire 32 X reg_array[28] [31:0] $end
     $var wire 32 Y reg_array[29] [31:0] $end
     $var wire 32 > reg_array[2] [31:0] $end
     $var wire 32 Z reg_array[30] [31:0] $end
     $var wire 32 [ reg_array[31] [31:0] $end
     $var wire 32 ? reg_array[3] [31:0] $end
     $var wire 32 @ reg_array[4] [31:0] $end
     $var wire 32 A reg_array[5] [31:0] $end
     $var wire 32 B reg_array[6] [31:0] $end
     $var wire 32 C reg_array[7] [31:0] $end
     $var wire 32 D reg_array[8] [31:0] $end
     $var wire 32 E reg_array[9] [31:0] $end
     $var wire  5 : rs1 [4:0] $end
     $var wire  5 9 rs2 [4:0] $end
    $upscope $end
   $upscope $end
  $upscope $end
 $upscope $end
$enddefinitions $end


#0
1#
0$
b00000000000000000000000000000000 %
b00000000000000000000000000000000 &
1'
b00000000000000000000000000000000 (
b00000000 )
b00000000 *
b00000000 +
b00000000 ,
b00000000000000000000000000000000 -
b00000000000000000000000000000000 .
b00000000000000000000000000000000 /
b00000000000000000000000000000000 0
b00000000000000000000000000000000 1
b00000000000000000000000000000000 2
b00 3
b0000000 4
b00000000000000000000000000000000 5
b00000000000000000000000000000000 6
b00000000000000000000000000000000 7
b00000000000000000000000000000000 8
b00000 9
b00000 :
b00000 ;
b00000000000000000000000000000000 <
b00000000000000000000000000000000 =
b00000000000000000000000000000000 >
b00000000000000000000000000000000 ?
b00000000000000000000000000000000 @
b00000000000000000000000000000000 A
b00000000000000000000000000000000 B
b00000000000000000000000000000000 C
b00000000000000000000000000000000 D
b00000000000000000000000000000000 E
b00000000000000000000000000000000 F
b00000000000000000000000000000000 G
b00000000000000000000000000000000 H
b00000000000000000000000000000000 I
b00000000000000000000000000000000 J
b00000000000000000000000000000000 K
b00000000000000000000000000000000 L
b00000000000000000000000000000000 M
b00000000000000000000000000000000 N
b00000000000000000000000000000000 O
b00000000000000000000000000000000 P
b00000000000000000000000000000000 Q
b00000000000000000000000000000000 R
b00000000000000000000000000000000 S
b00000000000000000000000000000000 T
b00000000000000000000000000000000 U
b00000000000000000000000000000000 V
b00000000000000000000000000000000 W
b00000000000000000000000000000000 X
b00000000000000000000000000000000 Y
b00000000000000000000000000000000 Z
b00000000000000000000000000000000 [
0\
0]
b00000000000000000000000000000000 ^
b00000000000000000000000000100000 _
b000 `
b00000000000000000000000000001000 a
b00000000000000000000000000000101 b
#1
b00000000000000000000000011111111 %
b00001111111100000000001100010011 &
0'
b11111111 )
b00000100 +
b00000000000000000000000011111111 .
b00000000000000000000000000000100 /
b00000000000000000000000000000100 0
b01 3
b0010011 4
b00000000000000000000000011111111 5
b00000000000000000000000011111111 7
b11111 9
b00110 ;
1\
#2
0\
#3
b00000000000000000000000000000000 %
b00000000000000000000010100010011 &
1'
b00000000000000000000000000000100 (
b00000000 )
b00000100 *
b00001000 +
b00000100 ,
b00000000000000000000000000000100 -
b00000000000000000000000000000000 .
b00000000000000000000000000001000 /
b00000000000000000000000000001000 0
b00000000000000000000000000000100 1
b00000000000000000000000000000100 2
b00000000000000000000000000000000 5
b00000000000000000000000000000000 7
b00000 9
b01010 ;
b00000000000000000000000011111111 B
1\
#4
0\
#5
b00000000000000000000010110010011 &
b00000000000000000000000000001000 (
b00001000 *
b00001100 +
b00001000 ,
b00000000000000000000000000001000 -
b00000000000000000000000000001100 /
b00000000000000000000000000001100 0
b00000000000000000000000000001000 1
b00000000000000000000000000001000 2
b01011 ;
1\
#6
0\
#7
b00000000000001011000010100010011 &
b00000000000000000000000000001100 (
b00001100 *
b00010000 +
b00001100 ,
b00000000000000000000000000001100 -
b00000000000000000000000000010000 /
b00000000000000000000000000010000 0
b00000000000000000000000000001100 1
b00000000000000000000000000001100 2
b01011 :
b01010 ;
1\
#8
0\
#9
b00000000000000000000000000000001 %
b00000000000101011000010110010011 &
0'
b00000000000000000000000000010000 (
b00000001 )
b00010000 *
b00010100 +
b00010000 ,
b00000000000000000000000000010000 -
b00000000000000000000000000000001 .
b00000000000000000000000000010100 /
b00000000000000000000000000010100 0
b00000000000000000000000000010000 1
b00000000000000000000000000010000 2
b00000000000000000000000000000001 5
b00000000000000000000000000000001 7
b00001 9
b01011 ;
1\
#10
0\
#11
0#
1$
b11111111111111111111111111111000 %
b11111110011001011001110011100011 &
b00000000000000000000000000010100 (
b11111000 )
b00010100 *
b00001100 +
b00010100 ,
b00000000000000000000000000010100 -
b00000000000000000000000011111000 .
b00000000000000000000000100001100 /
b00000000000000000000000000001100 0
b00000000000000000000000000010100 1
b00000000000000000000000000010100 2
b11 3
b1100011 4
b00000000000000000000000100000000 5
b00000000000000000000000000000001 6
b00000000000000000000000011111111 7
b00000000000000000000000011111111 8
b00110 9
b11001 ;
b00000000000000000000000000000001 G
1\
#12
0\
#13
1#
0$
b00000000000000000000000000000000 %
b00000000000001011000010100010011 &
b00000000000000000000000000001100 (
b00000000 )
b00001100 *
b00010000 +
b00001100 ,
b00000000000000000000000000001100 -
b00000000000000000000000000000000 .
b00000000000000000000000000010000 /
b00000000000000000000000000010000 0
b00000000000000000000000000001100 1
b00000000000000000000000000001100 2
b01 3
b0010011 4
b00000000000000000000000000000001 5
b00000000000000000000000000000000 7
b00000000000000000000000000000000 8
b00000 9
b01010 ;
1\
#14
0\
#15
b00000000000000000000000000000001 %
b00000000000101011000010110010011 &
1'
b00000000000000000000000000010000 (
b00000001 )
b00010000 *
b00010100 +
b00010000 ,
b00000000000000000000000000010000 -
b00000000000000000000000000000001 .
b00000000000000000000000000010100 /
b00000000000000000000000000010100 0
b00000000000000000000000000010000 1
b00000000000000000000000000010000 2
b00000000000000000000000000000010 5
b00000000000000000000000000000001 7
b00001 9
b01011 ;
b00000000000000000000000000000001 F
1\
b00000000000000000000000000000001 ^
#16
0\
#17
0#
1$
b11111111111111111111111111111000 %
b11111110011001011001110011100011 &
0'
b00000000000000000000000000010100 (
b11111000 )
b00010100 *
b00001100 +
b00010100 ,
b00000000000000000000000000010100 -
b00000000000000000000000011111000 .
b00000000000000000000000100001100 /
b00000000000000000000000000001100 0
b00000000000000000000000000010100 1
b00000000000000000000000000010100 2
b11 3
b1100011 4
b00000000000000000000000100000001 5
b00000000000000000000000000000010 6
b00000000000000000000000011111111 7
b00000000000000000000000011111111 8
b00110 9
b11001 ;
b00000000000000000000000000000010 G
1\
#18
0\
#19
1#
0$
b00000000000000000000000000000000 %
b00000000000001011000010100010011 &
b00000000000000000000000000001100 (
b00000000 )
b00001100 *
b00010000 +
b00001100 ,
b00000000000000000000000000001100 -
b00000000000000000000000000000000 .
b00000000000000000000000000010000 /
b00000000000000000000000000010000 0
b00000000000000000000000000001100 1
b00000000000000000000000000001100 2
b01 3
b0010011 4
b00000000000000000000000000000010 5
b00000000000000000000000000000000 7
b00000000000000000000000000000000 8
b00000 9
b01010 ;
1\
#20
0\
#21
b00000000000000000000000000000001 %
b00000000000101011000010110010011 &
b00000000000000000000000000010000 (
b00000001 )
b00010000 *
b00010100 +
b00010000 ,
b00000000000000000000000000010000 -
b00000000000000000000000000000001 .
b00000000000000000000000000010100 /
b00000000000000000000000000010100 0
b00000000000000000000000000010000 1
b00000000000000000000000000010000 2
b00000000000000000000000000000011 5
b00000000000000000000000000000001 7
b00001 9
b01011 ;
b00000000000000000000000000000010 F
1\
b00000000000000000000000000000010 ^
#22
0\
#23
0#
1$
b11111111111111111111111111111000 %
b11111110011001011001110011100011 &
b00000000000000000000000000010100 (
b11111000 )
b00010100 *
b00001100 +
b00010100 ,
b00000000000000000000000000010100 -
b00000000000000000000000011111000 .
b00000000000000000000000100001100 /
b00000000000000000000000000001100 0
b00000000000000000000000000010100 1
b00000000000000000000000000010100 2
b11 3
b1100011 4
b00000000000000000000000100000010 5
b00000000000000000000000000000011 6
b00000000000000000000000011111111 7
b00000000000000000000000011111111 8
b00110 9
b11001 ;
b00000000000000000000000000000011 G
1\
#24
0\
#25
1#
0$
b00000000000000000000000000000000 %
b00000000000001011000010100010011 &
b00000000000000000000000000001100 (
b00000000 )
b00001100 *
b00010000 +
b00001100 ,
b00000000000000000000000000001100 -
b00000000000000000000000000000000 .
b00000000000000000000000000010000 /
b00000000000000000000000000010000 0
b00000000000000000000000000001100 1
b00000000000000000000000000001100 2
b01 3
b0010011 4
b00000000000000000000000000000011 5
b00000000000000000000000000000000 7
b00000000000000000000000000000000 8
b00000 9
b01010 ;
1\
#26
0\
#27
b00000000000000000000000000000001 %
b00000000000101011000010110010011 &
b00000000000000000000000000010000 (
b00000001 )
b00010000 *
b00010100 +
b00010000 ,
b00000000000000000000000000010000 -
b00000000000000000000000000000001 .
b00000000000000000000000000010100 /
b00000000000000000000000000010100 0
b00000000000000000000000000010000 1
b00000000000000000000000000010000 2
b00000000000000000000000000000100 5
b00000000000000000000000000000001 7
b00001 9
b01011 ;
b00000000000000000000000000000011 F
1\
b00000000000000000000000000000011 ^
#28
0\
#29
0#
1$
b11111111111111111111111111111000 %
b11111110011001011001110011100011 &
b00000000000000000000000000010100 (
b11111000 )
b00010100 *
b00001100 +
b00010100 ,
b00000000000000000000000000010100 -
b00000000000000000000000011111000 .
b00000000000000000000000100001100 /
b00000000000000000000000000001100 0
b00000000000000000000000000010100 1
b00000000000000000000000000010100 2
b11 3
b1100011 4
b00000000000000000000000100000011 5
b00000000000000000000000000000100 6
b00000000000000000000000011111111 7
b00000000000000000000000011111111 8
b00110 9
b11001 ;
b00000000000000000000000000000100 G
1\
#30
0\
#31
1#
0$
b00000000000000000000000000000000 %
b00000000000001011000010100010011 &
b00000000000000000000000000001100 (
b00000000 )
b00001100 *
b00010000 +
b00001100 ,
b00000000000000000000000000001100 -
b00000000000000000000000000000000 .
b00000000000000000000000000010000 /
b00000000000000000000000000010000 0
b00000000000000000000000000001100 1
b00000000000000000000000000001100 2
b01 3
b0010011 4
b00000000000000000000000000000100 5
b00000000000000000000000000000000 7
b00000000000000000000000000000000 8
b00000 9
b01010 ;
1\
#32
0\
#33
b00000000000000000000000000000001 %
b00000000000101011000010110010011 &
b00000000000000000000000000010000 (
b00000001 )
b00010000 *
b00010100 +
b00010000 ,
b00000000000000000000000000010000 -
b00000000000000000000000000000001 .
b00000000000000000000000000010100 /
b00000000000000000000000000010100 0
b00000000000000000000000000010000 1
b00000000000000000000000000010000 2
b00000000000000000000000000000101 5
b00000000000000000000000000000001 7
b00001 9
b01011 ;
b00000000000000000000000000000100 F
1\
b00000000000000000000000000000100 ^
#34
0\
#35
0#
1$
b11111111111111111111111111111000 %
b11111110011001011001110011100011 &
b00000000000000000000000000010100 (
b11111000 )
b00010100 *
b00001100 +
b00010100 ,
b00000000000000000000000000010100 -
b00000000000000000000000011111000 .
b00000000000000000000000100001100 /
b00000000000000000000000000001100 0
b00000000000000000000000000010100 1
b00000000000000000000000000010100 2
b11 3
b1100011 4
b00000000000000000000000100000100 5
b00000000000000000000000000000101 6
b00000000000000000000000011111111 7
b00000000000000000000000011111111 8
b00110 9
b11001 ;
b00000000000000000000000000000101 G
1\
#36
0\
#37
1#
0$
b00000000000000000000000000000000 %
b00000000000001011000010100010011 &
b00000000000000000000000000001100 (
b00000000 )
b00001100 *
b00010000 +
b00001100 ,
b00000000000000000000000000001100 -
b00000000000000000000000000000000 .
b00000000000000000000000000010000 /
b00000000000000000000000000010000 0
b00000000000000000000000000001100 1
b00000000000000000000000000001100 2
b01 3
b0010011 4
b00000000000000000000000000000101 5
b00000000000000000000000000000000 7
b00000000000000000000000000000000 8
b00000 9
b01010 ;
1\
#38
0\
#39
b00000000000000000000000000000001 %
b00000000000101011000010110010011 &
b00000000000000000000000000010000 (
b00000001 )
b00010000 *
b00010100 +
b00010000 ,
b00000000000000000000000000010000 -
b00000000000000000000000000000001 .
b00000000000000000000000000010100 /
b00000000000000000000000000010100 0
b00000000000000000000000000010000 1
b00000000000000000000000000010000 2
b00000000000000000000000000000110 5
b00000000000000000000000000000001 7
b00001 9
b01011 ;
b00000000000000000000000000000101 F
1\
b00000000000000000000000000000101 ^
#40
0\
#41
0#
1$
b11111111111111111111111111111000 %
b11111110011001011001110011100011 &
b00000000000000000000000000010100 (
b11111000 )
b00010100 *
b00001100 +
b00010100 ,
b00000000000000000000000000010100 -
b00000000000000000000000011111000 .
b00000000000000000000000100001100 /
b00000000000000000000000000001100 0
b00000000000000000000000000010100 1
b00000000000000000000000000010100 2
b11 3
b1100011 4
b00000000000000000000000100000101 5
b00000000000000000000000000000110 6
b00000000000000000000000011111111 7
b00000000000000000000000011111111 8
b00110 9
b11001 ;
b00000000000000000000000000000110 G
1\
#42
0\
#43
1#
0$
b00000000000000000000000000000000 %
b00000000000001011000010100010011 &
b00000000000000000000000000001100 (
b00000000 )
b00001100 *
b00010000 +
b00001100 ,
b00000000000000000000000000001100 -
b00000000000000000000000000000000 .
b00000000000000000000000000010000 /
b00000000000000000000000000010000 0
b00000000000000000000000000001100 1
b00000000000000000000000000001100 2
b01 3
b0010011 4
b00000000000000000000000000000110 5
b00000000000000000000000000000000 7
b00000000000000000000000000000000 8
b00000 9
b01010 ;
1\
#44
0\
#45
b00000000000000000000000000000001 %
b00000000000101011000010110010011 &
b00000000000000000000000000010000 (
b00000001 )
b00010000 *
b00010100 +
b00010000 ,
b00000000000000000000000000010000 -
b00000000000000000000000000000001 .
b00000000000000000000000000010100 /
b00000000000000000000000000010100 0
b00000000000000000000000000010000 1
b00000000000000000000000000010000 2
b00000000000000000000000000000111 5
b00000000000000000000000000000001 7
b00001 9
b01011 ;
b00000000000000000000000000000110 F
1\
b00000000000000000000000000000110 ^
#46
0\
#47
0#
1$
b11111111111111111111111111111000 %
b11111110011001011001110011100011 &
b00000000000000000000000000010100 (
b11111000 )
b00010100 *
b00001100 +
b00010100 ,
b00000000000000000000000000010100 -
b00000000000000000000000011111000 .
b00000000000000000000000100001100 /
b00000000000000000000000000001100 0
b00000000000000000000000000010100 1
b00000000000000000000000000010100 2
b11 3
b1100011 4
b00000000000000000000000100000110 5
b00000000000000000000000000000111 6
b00000000000000000000000011111111 7
b00000000000000000000000011111111 8
b00110 9
b11001 ;
b00000000000000000000000000000111 G
1\
#48
0\
#49
1#
0$
b00000000000000000000000000000000 %
b00000000000001011000010100010011 &
b00000000000000000000000000001100 (
b00000000 )
b00001100 *
b00010000 +
b00001100 ,
b00000000000000000000000000001100 -
b00000000000000000000000000000000 .
b00000000000000000000000000010000 /
b00000000000000000000000000010000 0
b00000000000000000000000000001100 1
b00000000000000000000000000001100 2
b01 3
b0010011 4
b00000000000000000000000000000111 5
b00000000000000000000000000000000 7
b00000000000000000000000000000000 8
b00000 9
b01010 ;
1\
#50
0\
#51
b00000000000000000000000000000001 %
b00000000000101011000010110010011 &
b00000000000000000000000000010000 (
b00000001 )
b00010000 *
b00010100 +
b00010000 ,
b00000000000000000000000000010000 -
b00000000000000000000000000000001 .
b00000000000000000000000000010100 /
b00000000000000000000000000010100 0
b00000000000000000000000000010000 1
b00000000000000000000000000010000 2
b00000000000000000000000000001000 5
b00000000000000000000000000000001 7
b00001 9
b01011 ;
b00000000000000000000000000000111 F
1\
b00000000000000000000000000000111 ^
#52
0\
