reduced_risc_v/cpu_test_old/pc_reg.sv
module pc_reg #(
    parameter WIDTH = 32
)(
    input logic clk, 
    input logic rst, 
    input logic [WIDTH-1:0] next_PC,
    output logic [WIDTH-1:0] pc,

    output logic [WIDTH-1:0] another_pc
);

always_ff @ (posedge clk)
begin
    if (rst)
        pc <= {WIDTH{1'b0}};
    else
        pc <= next_PC;

    another_pc <= next_PC;
end

endmodule

reduced_risc_v/pc/pc_mux.sv
module pc_mux #(
    parameter WIDTH = 32
)(
    input logic clk,
    input logic PCsrc,
    input logic [WIDTH-1:0] pc ,
    input logic [WIDTH-1:0] ImmOp,
    output logic [WIDTH-1:0] next_PC
);

    assign next_PC = PCsrc ? pc + ImmOp : pc + 32'd4;

endmodule

reduced_risc_v/cpu_test_old/pc_top.sv
module pc_top #(
    parameter   WIDTH = 8
)(
    // interface signals
    input   logic                       clk,        // clock
    input   logic                       rst,        // reset        
    input   logic [WIDTH-1:0]           ImmOp,     
    input   logic                       PCsrc,
    output logic [WIDTH-1:0]            pc_out
);

logic [WIDTH-1:0]   next_PC, pc;    // interconnect wire

pc_mux pc_mux(
    //.clk (clk),
    .PCsrc (PCsrc),
    .ImmOp (ImmOp),
    .next_PC (next_PC),
    .pc (pc)
);

pc_reg pc_reg(
    .clk (clk),
    .rst (rst),
    .next_PC (next_PC),
    .pc (pc),
    .another_pc(pc_out)
);

endmodule

reduced_risc_v/cpu_test_old/pc_top.vcd
$version Generated by VerilatedVcd $end
$date Fri Nov 24 15:20:44 2023 $end
$timescale 1ps $end

 $scope module TOP $end
  $var wire 32 % ImmOp [31:0] $end
  $var wire  1 & PCsrc $end
  $var wire  1 # clk $end
  $var wire 32 ' pc_out [31:0] $end
  $var wire  1 $ rst $end
  $scope module pc_top $end
   $var wire 32 % ImmOp [31:0] $end
   $var wire  1 & PCsrc $end
   $var wire 32 * WIDTH [31:0] $end
   $var wire  1 # clk $end
   $var wire 32 ( next_PC [31:0] $end
   $var wire 32 ) pc [31:0] $end
   $var wire 32 ' pc_out [31:0] $end
   $var wire  1 $ rst $end
   $scope module pc_mux $end
    $var wire 32 % ImmOp [31:0] $end
    $var wire  1 & PCsrc $end
    $var wire 32 * WIDTH [31:0] $end
    $var wire  1 # clk $end
    $var wire 32 ( next_PC [31:0] $end
    $var wire 32 ) pc [31:0] $end
   $upscope $end
   $scope module pc_reg $end
    $var wire 32 * WIDTH [31:0] $end
    $var wire 32 ' another_pc [31:0] $end
    $var wire  1 # clk $end
    $var wire 32 ( next_PC [31:0] $end
    $var wire 32 ) pc [31:0] $end
    $var wire  1 $ rst $end
   $upscope $end
  $upscope $end
 $upscope $end
$enddefinitions $end


#0
0#
0$
b00000000000000000000000000000001 %
0&
b00000000000000000000000000000000 '
b00000000000000000000000000000000 (
b00000000000000000000000000000000 )
b00000000000000000000000000100000 *
#1
1#
b00000000000000000000000000000100 (
#2
0#
#3
1#
b00000000000000000000000000000100 '
b00000000000000000000000000001000 (
b00000000000000000000000000000100 )
#4
0#
#5
1#
b00000000000000000000000000001000 '
b00000000000000000000000000001100 (
b00000000000000000000000000001000 )
#6
0#
#7
1#
b00000000000000000000000000001100 '
b00000000000000000000000000010000 (
b00000000000000000000000000001100 )
#8
0#
#9
1#
b00000000000000000000000000010000 '
b00000000000000000000000000010100 (
b00000000000000000000000000010000 )
#10
0#
#11
1#
b00000000000000000000000000010100 '
b00000000000000000000000000011000 (
b00000000000000000000000000010100 )
#12
0#
#13
1#
b00000000000000000000000000011000 '
b00000000000000000000000000011100 (
b00000000000000000000000000011000 )
#14
0#
#15
1#
b00000000000000000000000000011100 '
b00000000000000000000000000100000 (
b00000000000000000000000000011100 )
#16
0#
#17
1#
b00000000000000000000000000100000 '
b00000000000000000000000000100100 (
b00000000000000000000000000100000 )
#18
0#
#19
1#
b00000000000000000000000000100100 '
b00000000000000000000000000101000 (
b00000000000000000000000000100100 )
#20
0#
#21
1#
b00000000000000000000000000101000 '
b00000000000000000000000000101100 (
b00000000000000000000000000101000 )
#22
0#
#23
1#
b00000000000000000000000000101100 '
b00000000000000000000000000110000 (
b00000000000000000000000000101100 )
#24
0#
#25
1#
b00000000000000000000000000110000 '
b00000000000000000000000000110100 (
b00000000000000000000000000110000 )
#26
0#
#27
1#
b00000000000000000000000000110100 '
b00000000000000000000000000111000 (
b00000000000000000000000000110100 )
#28
0#
#29
1#
b00000000000000000000000000111000 '
b00000000000000000000000000111100 (
b00000000000000000000000000111000 )
#30
0#
#31
1#
b00000000000000000000000000111100 '
b00000000000000000000000001000000 (
b00000000000000000000000000111100 )
#32
0#
#33
1#
b00000000000000000000000001000000 '
b00000000000000000000000001000100 (
b00000000000000000000000001000000 )
#34
0#
#35
1#
b00000000000000000000000001000100 '
b00000000000000000000000001001000 (
b00000000000000000000000001000100 )
#36
0#
#37
1#
b00000000000000000000000001001000 '
b00000000000000000000000001001100 (
b00000000000000000000000001001000 )
#38
0#
#39
1#
b00000000000000000000000001001100 '
b00000000000000000000000001010000 (
b00000000000000000000000001001100 )
#40
0#
#41
1#
b00000000000000000000000001010000 '
b00000000000000000000000001010100 (
b00000000000000000000000001010000 )
#42
0#
#43
1#
b00000000000000000000000001010100 '
b00000000000000000000000001011000 (
b00000000000000000000000001010100 )
#44
0#
#45
1#
b00000000000000000000000001011000 '
b00000000000000000000000001011100 (
b00000000000000000000000001011000 )
#46
0#
#47
1#
b00000000000000000000000001011100 '
b00000000000000000000000001100000 (
b00000000000000000000000001011100 )
#48
0#
#49
1#
b00000000000000000000000001100000 '
b00000000000000000000000001100100 (
b00000000000000000000000001100000 )
#50
0#
#51
1#
b00000000000000000000000001100100 '
b00000000000000000000000001101000 (
b00000000000000000000000001100100 )
#52
0#
#53
1#
b00000000000000000000000001101000 '
b00000000000000000000000001101100 (
b00000000000000000000000001101000 )
#54
0#
#55
1#
b00000000000000000000000001101100 '
b00000000000000000000000001110000 (
b00000000000000000000000001101100 )
#56
0#
#57
1#
b00000000000000000000000001110000 '
b00000000000000000000000001110100 (
b00000000000000000000000001110000 )
#58
0#
#59
1#
b00000000000000000000000001110100 '
b00000000000000000000000001111000 (
b00000000000000000000000001110100 )
#60
0#
#61
1#
b00000000000000000000000001111000 '
b00000000000000000000000001111100 (
b00000000000000000000000001111000 )
#62
0#
#63
1#
b00000000000000000000000001111100 '
b00000000000000000000000010000000 (
b00000000000000000000000001111100 )
#64
0#
#65
1#
b00000000000000000000000010000000 '
b00000000000000000000000010000100 (
b00000000000000000000000010000000 )
#66
0#
#67
1#
b00000000000000000000000010000100 '
b00000000000000000000000010001000 (
b00000000000000000000000010000100 )
#68
0#
#69
1#
b00000000000000000000000010001000 '
b00000000000000000000000010001100 (
b00000000000000000000000010001000 )
#70
0#
#71
1#
b00000000000000000000000010001100 '
b00000000000000000000000010010000 (
b00000000000000000000000010001100 )
#72
0#
#73
1#
b00000000000000000000000010010000 '
b00000000000000000000000010010100 (
b00000000000000000000000010010000 )
#74
0#
#75
1#
b00000000000000000000000010010100 '
b00000000000000000000000010011000 (
b00000000000000000000000010010100 )
#76
0#
#77
1#
b00000000000000000000000010011000 '
b00000000000000000000000010011100 (
b00000000000000000000000010011000 )
#78
0#
#79
1#
b00000000000000000000000010011100 '
b00000000000000000000000010100000 (
b00000000000000000000000010011100 )
#80
0#
#81
1#
b00000000000000000000000010100000 '
b00000000000000000000000010100100 (
b00000000000000000000000010100000 )
#82
0#
#83
1#
b00000000000000000000000010100100 '
b00000000000000000000000010101000 (
b00000000000000000000000010100100 )
#84
0#
#85
1#
b00000000000000000000000010101000 '
b00000000000000000000000010101100 (
b00000000000000000000000010101000 )
#86
0#
#87
1#
b00000000000000000000000010101100 '
b00000000000000000000000010110000 (
b00000000000000000000000010101100 )
#88
0#
#89
1#
b00000000000000000000000010110000 '
b00000000000000000000000010110100 (
b00000000000000000000000010110000 )
#90
0#
#91
1#
b00000000000000000000000010110100 '
b00000000000000000000000010111000 (
b00000000000000000000000010110100 )
#92
0#
#93
1#
b00000000000000000000000010111000 '
b00000000000000000000000010111100 (
b00000000000000000000000010111000 )
#94
0#
#95
1#
b00000000000000000000000010111100 '
b00000000000000000000000011000000 (
b00000000000000000000000010111100 )
#96
0#
#97
1#
b00000000000000000000000011000000 '
b00000000000000000000000011000100 (
b00000000000000000000000011000000 )
#98
0#
#99
1#
b00000000000000000000000011000100 '
b00000000000000000000000011001000 (
b00000000000000000000000011000100 )
#100
0#
#101
1#
b00000000000000000000000011001000 '
b00000000000000000000000011001100 (
b00000000000000000000000011001000 )
#102
0#
#103
1#
b00000000000000000000000011001100 '
b00000000000000000000000011010000 (
b00000000000000000000000011001100 )
#104
0#
#105
1#
b00000000000000000000000011010000 '
b00000000000000000000000011010100 (
b00000000000000000000000011010000 )
#106
0#
#107
1#
b00000000000000000000000011010100 '
b00000000000000000000000011011000 (
b00000000000000000000000011010100 )
#108
0#
#109
1#
b00000000000000000000000011011000 '
b00000000000000000000000011011100 (
b00000000000000000000000011011000 )
#110
0#
#111
1#
b00000000000000000000000011011100 '
b00000000000000000000000011100000 (
b00000000000000000000000011011100 )
#112
0#
#113
1#
b00000000000000000000000011100000 '
b00000000000000000000000011100100 (
b00000000000000000000000011100000 )
#114
0#
#115
1#
b00000000000000000000000011100100 '
b00000000000000000000000011101000 (
b00000000000000000000000011100100 )
#116
0#
#117
1#
b00000000000000000000000011101000 '
b00000000000000000000000011101100 (
b00000000000000000000000011101000 )
#118
0#
#119
1#
b00000000000000000000000011101100 '
b00000000000000000000000011110000 (
b00000000000000000000000011101100 )
#120
0#
#121
1#
b00000000000000000000000011110000 '
b00000000000000000000000011110100 (
b00000000000000000000000011110000 )
#122
0#
#123
1#
b00000000000000000000000011110100 '
b00000000000000000000000011111000 (
b00000000000000000000000011110100 )
#124
0#
#125
1#
b00000000000000000000000011111000 '
b00000000000000000000000011111100 (
b00000000000000000000000011111000 )
#126
0#
#127
1#
b00000000000000000000000011111100 '
b00000000000000000000000100000000 (
b00000000000000000000000011111100 )
#128
0#
#129
1#
b00000000000000000000000100000000 '
b00000000000000000000000100000100 (
b00000000000000000000000100000000 )
#130
0#
#131
1#
b00000000000000000000000100000100 '
b00000000000000000000000100001000 (
b00000000000000000000000100000100 )
#132
0#
#133
1#
b00000000000000000000000100001000 '
b00000000000000000000000100001100 (
b00000000000000000000000100001000 )
#134
0#
#135
1#
b00000000000000000000000100001100 '
b00000000000000000000000100010000 (
b00000000000000000000000100001100 )
#136
0#
#137
1#
b00000000000000000000000100010000 '
b00000000000000000000000100010100 (
b00000000000000000000000100010000 )
#138
0#
#139
1#
b00000000000000000000000100010100 '
b00000000000000000000000100011000 (
b00000000000000000000000100010100 )
#140
0#
#141
1#
b00000000000000000000000100011000 '
b00000000000000000000000100011100 (
b00000000000000000000000100011000 )
#142
0#
#143
1#
b00000000000000000000000100011100 '
b00000000000000000000000100100000 (
b00000000000000000000000100011100 )
#144
0#
#145
1#
b00000000000000000000000100100000 '
b00000000000000000000000100100100 (
b00000000000000000000000100100000 )
#146
0#
#147
1#
b00000000000000000000000100100100 '
b00000000000000000000000100101000 (
b00000000000000000000000100100100 )
#148
0#
#149
1#
b00000000000000000000000100101000 '
b00000000000000000000000100101100 (
b00000000000000000000000100101000 )
#150
0#
#151
1#
b00000000000000000000000100101100 '
b00000000000000000000000100110000 (
b00000000000000000000000100101100 )
#152
0#
#153
1#
b00000000000000000000000100110000 '
b00000000000000000000000100110100 (
b00000000000000000000000100110000 )
#154
0#
#155
1#
b00000000000000000000000100110100 '
b00000000000000000000000100111000 (
b00000000000000000000000100110100 )
#156
0#
#157
1#
b00000000000000000000000100111000 '
b00000000000000000000000100111100 (
b00000000000000000000000100111000 )
#158
0#
#159
1#
b00000000000000000000000100111100 '
b00000000000000000000000101000000 (
b00000000000000000000000100111100 )
#160
0#
#161
1#
b00000000000000000000000101000000 '
b00000000000000000000000101000100 (
b00000000000000000000000101000000 )
#162
0#
#163
1#
b00000000000000000000000101000100 '
b00000000000000000000000101001000 (
b00000000000000000000000101000100 )
#164
0#
#165
1#
b00000000000000000000000101001000 '
b00000000000000000000000101001100 (
b00000000000000000000000101001000 )
#166
0#
#167
1#
b00000000000000000000000101001100 '
b00000000000000000000000101010000 (
b00000000000000000000000101001100 )
#168
0#
#169
1#
b00000000000000000000000101010000 '
b00000000000000000000000101010100 (
b00000000000000000000000101010000 )
#170
0#
#171
1#
b00000000000000000000000101010100 '
b00000000000000000000000101011000 (
b00000000000000000000000101010100 )
#172
0#
#173
1#
b00000000000000000000000101011000 '
b00000000000000000000000101011100 (
b00000000000000000000000101011000 )
#174
0#
#175
1#
b00000000000000000000000101011100 '
b00000000000000000000000101100000 (
b00000000000000000000000101011100 )
#176
0#
#177
1#
b00000000000000000000000101100000 '
b00000000000000000000000101100100 (
b00000000000000000000000101100000 )
#178
0#
#179
1#
b00000000000000000000000101100100 '
b00000000000000000000000101101000 (
b00000000000000000000000101100100 )
#180
0#
#181
1#
b00000000000000000000000101101000 '
b00000000000000000000000101101100 (
b00000000000000000000000101101000 )
#182
0#
#183
1#
b00000000000000000000000101101100 '
b00000000000000000000000101110000 (
b00000000000000000000000101101100 )
#184
0#
#185
1#
b00000000000000000000000101110000 '
b00000000000000000000000101110100 (
b00000000000000000000000101110000 )
#186
0#
#187
1#
b00000000000000000000000101110100 '
b00000000000000000000000101111000 (
b00000000000000000000000101110100 )
#188
0#
#189
1#
b00000000000000000000000101111000 '
b00000000000000000000000101111100 (
b00000000000000000000000101111000 )
#190
0#
#191
1#
b00000000000000000000000101111100 '
b00000000000000000000000110000000 (
b00000000000000000000000101111100 )
#192
0#
#193
1#
b00000000000000000000000110000000 '
b00000000000000000000000110000100 (
b00000000000000000000000110000000 )
#194
0#
#195
1#
b00000000000000000000000110000100 '
b00000000000000000000000110001000 (
b00000000000000000000000110000100 )
#196
0#
#197
1#
b00000000000000000000000110001000 '
b00000000000000000000000110001100 (
b00000000000000000000000110001000 )
#198
0#
#199
1#
b00000000000000000000000110001100 '
b00000000000000000000000110010000 (
b00000000000000000000000110001100 )
#200
0#
#201
1#
b00000000000000000000000110010000 '
b00000000000000000000000110010100 (
b00000000000000000000000110010000 )
#202
0#
#203
1#
b00000000000000000000000110010100 '
b00000000000000000000000110011000 (
b00000000000000000000000110010100 )
#204
0#
#205
1#
b00000000000000000000000110011000 '
b00000000000000000000000110011100 (
b00000000000000000000000110011000 )
#206
0#
#207
1#
b00000000000000000000000110011100 '
b00000000000000000000000110100000 (
b00000000000000000000000110011100 )
#208
0#
#209
1#
b00000000000000000000000110100000 '
b00000000000000000000000110100100 (
b00000000000000000000000110100000 )
#210
0#
#211
1#
b00000000000000000000000110100100 '
b00000000000000000000000110101000 (
b00000000000000000000000110100100 )
#212
0#
#213
1#
b00000000000000000000000110101000 '
b00000000000000000000000110101100 (
b00000000000000000000000110101000 )
#214
0#
#215
1#
b00000000000000000000000110101100 '
b00000000000000000000000110110000 (
b00000000000000000000000110101100 )
#216
0#
#217
1#
b00000000000000000000000110110000 '
b00000000000000000000000110110100 (
b00000000000000000000000110110000 )
#218
0#
#219
1#
b00000000000000000000000110110100 '
b00000000000000000000000110111000 (
b00000000000000000000000110110100 )
#220
0#
#221
1#
b00000000000000000000000110111000 '
b00000000000000000000000110111100 (
b00000000000000000000000110111000 )
#222
0#
#223
1#
b00000000000000000000000110111100 '
b00000000000000000000000111000000 (
b00000000000000000000000110111100 )
#224
0#
#225
1#
b00000000000000000000000111000000 '
b00000000000000000000000111000100 (
b00000000000000000000000111000000 )
#226
0#
#227
1#
b00000000000000000000000111000100 '
b00000000000000000000000111001000 (
b00000000000000000000000111000100 )
#228
0#
#229
1#
b00000000000000000000000111001000 '
b00000000000000000000000111001100 (
b00000000000000000000000111001000 )
#230
0#
#231
1#
b00000000000000000000000111001100 '
b00000000000000000000000111010000 (
b00000000000000000000000111001100 )
#232
0#
#233
1#
b00000000000000000000000111010000 '
b00000000000000000000000111010100 (
b00000000000000000000000111010000 )
#234
0#
#235
1#
b00000000000000000000000111010100 '
b00000000000000000000000111011000 (
b00000000000000000000000111010100 )
#236
0#
#237
1#
b00000000000000000000000111011000 '
b00000000000000000000000111011100 (
b00000000000000000000000111011000 )
#238
0#
#239
1#
b00000000000000000000000111011100 '
b00000000000000000000000111100000 (
b00000000000000000000000111011100 )
#240
0#
#241
1#
b00000000000000000000000111100000 '
b00000000000000000000000111100100 (
b00000000000000000000000111100000 )
#242
0#
#243
1#
b00000000000000000000000111100100 '
b00000000000000000000000111101000 (
b00000000000000000000000111100100 )
#244
0#
#245
1#
b00000000000000000000000111101000 '
b00000000000000000000000111101100 (
b00000000000000000000000111101000 )
#246
0#
#247
1#
b00000000000000000000000111101100 '
b00000000000000000000000111110000 (
b00000000000000000000000111101100 )
#248
0#
#249
1#
b00000000000000000000000111110000 '
b00000000000000000000000111110100 (
b00000000000000000000000111110000 )
#250
0#
#251
1#
b00000000000000000000000111110100 '
b00000000000000000000000111111000 (
b00000000000000000000000111110100 )
#252
0#
#253
1#
b00000000000000000000000111111000 '
b00000000000000000000000111111100 (
b00000000000000000000000111111000 )
#254
0#
#255
1#
b00000000000000000000000111111100 '
b00000000000000000000001000000000 (
b00000000000000000000000111111100 )
#256
0#
#257
1#
b00000000000000000000001000000000 '
b00000000000000000000001000000100 (
b00000000000000000000001000000000 )
#258
0#
#259
1#
b00000000000000000000001000000100 '
b00000000000000000000001000001000 (
b00000000000000000000001000000100 )
#260
0#
#261
1#
b00000000000000000000001000001000 '
b00000000000000000000001000001100 (
b00000000000000000000001000001000 )
#262
0#
#263
1#
b00000000000000000000001000001100 '
b00000000000000000000001000010000 (
b00000000000000000000001000001100 )
#264
0#
#265
1#
b00000000000000000000001000010000 '
b00000000000000000000001000010100 (
b00000000000000000000001000010000 )
#266
0#
#267
1#
b00000000000000000000001000010100 '
b00000000000000000000001000011000 (
b00000000000000000000001000010100 )
#268
0#
#269
1#
b00000000000000000000001000011000 '
b00000000000000000000001000011100 (
b00000000000000000000001000011000 )
#270
0#
#271
1#
b00000000000000000000001000011100 '
b00000000000000000000001000100000 (
b00000000000000000000001000011100 )
#272
0#
#273
1#
b00000000000000000000001000100000 '
b00000000000000000000001000100100 (
b00000000000000000000001000100000 )
#274
0#
#275
1#
b00000000000000000000001000100100 '
b00000000000000000000001000101000 (
b00000000000000000000001000100100 )
#276
0#
#277
1#
b00000000000000000000001000101000 '
b00000000000000000000001000101100 (
b00000000000000000000001000101000 )
#278
0#
#279
1#
b00000000000000000000001000101100 '
b00000000000000000000001000110000 (
b00000000000000000000001000101100 )
#280
0#
#281
1#
b00000000000000000000001000110000 '
b00000000000000000000001000110100 (
b00000000000000000000001000110000 )
#282
0#
#283
1#
b00000000000000000000001000110100 '
b00000000000000000000001000111000 (
b00000000000000000000001000110100 )
#284
0#
#285
1#
b00000000000000000000001000111000 '
b00000000000000000000001000111100 (
b00000000000000000000001000111000 )
#286
0#
#287
1#
b00000000000000000000001000111100 '
b00000000000000000000001001000000 (
b00000000000000000000001000111100 )
#288
0#
#289
1#
b00000000000000000000001001000000 '
b00000000000000000000001001000100 (
b00000000000000000000001001000000 )
#290
0#
#291
1#
b00000000000000000000001001000100 '
b00000000000000000000001001001000 (
b00000000000000000000001001000100 )
#292
0#
#293
1#
b00000000000000000000001001001000 '
b00000000000000000000001001001100 (
b00000000000000000000001001001000 )
#294
0#
#295
1#
b00000000000000000000001001001100 '
b00000000000000000000001001010000 (
b00000000000000000000001001001100 )
#296
0#
#297
1#
b00000000000000000000001001010000 '
b00000000000000000000001001010100 (
b00000000000000000000001001010000 )
#298
0#
#299
1#
b00000000000000000000001001010100 '
b00000000000000000000001001011000 (
b00000000000000000000001001010100 )
#300
0#
#301
1#
b00000000000000000000001001011000 '
b00000000000000000000001001011100 (
b00000000000000000000001001011000 )
#302
0#
#303
1#
b00000000000000000000001001011100 '
b00000000000000000000001001100000 (
b00000000000000000000001001011100 )
#304
0#
#305
1#
b00000000000000000000001001100000 '
b00000000000000000000001001100100 (
b00000000000000000000001001100000 )
#306
0#
#307
1#
b00000000000000000000001001100100 '
b00000000000000000000001001101000 (
b00000000000000000000001001100100 )
#308
0#
#309
1#
b00000000000000000000001001101000 '
b00000000000000000000001001101100 (
b00000000000000000000001001101000 )
#310
0#
#311
1#
b00000000000000000000001001101100 '
b00000000000000000000001001110000 (
b00000000000000000000001001101100 )
#312
0#
#313
1#
b00000000000000000000001001110000 '
b00000000000000000000001001110100 (
b00000000000000000000001001110000 )
#314
0#
#315
1#
b00000000000000000000001001110100 '
b00000000000000000000001001111000 (
b00000000000000000000001001110100 )
#316
0#
#317
1#
b00000000000000000000001001111000 '
b00000000000000000000001001111100 (
b00000000000000000000001001111000 )
#318
0#
#319
1#
b00000000000000000000001001111100 '
b00000000000000000000001010000000 (
b00000000000000000000001001111100 )
#320
0#
#321
1#
b00000000000000000000001010000000 '
b00000000000000000000001010000100 (
b00000000000000000000001010000000 )
#322
0#
#323
1#
b00000000000000000000001010000100 '
b00000000000000000000001010001000 (
b00000000000000000000001010000100 )
#324
0#
#325
1#
b00000000000000000000001010001000 '
b00000000000000000000001010001100 (
b00000000000000000000001010001000 )
#326
0#
#327
1#
b00000000000000000000001010001100 '
b00000000000000000000001010010000 (
b00000000000000000000001010001100 )
#328
0#
#329
1#
b00000000000000000000001010010000 '
b00000000000000000000001010010100 (
b00000000000000000000001010010000 )
#330
0#
#331
1#
b00000000000000000000001010010100 '
b00000000000000000000001010011000 (
b00000000000000000000001010010100 )
#332
0#
#333
1#
b00000000000000000000001010011000 '
b00000000000000000000001010011100 (
b00000000000000000000001010011000 )
#334
0#
#335
1#
b00000000000000000000001010011100 '
b00000000000000000000001010100000 (
b00000000000000000000001010011100 )
#336
0#
#337
1#
b00000000000000000000001010100000 '
b00000000000000000000001010100100 (
b00000000000000000000001010100000 )
#338
0#
#339
1#
b00000000000000000000001010100100 '
b00000000000000000000001010101000 (
b00000000000000000000001010100100 )
#340
0#
#341
1#
b00000000000000000000001010101000 '
b00000000000000000000001010101100 (
b00000000000000000000001010101000 )
#342
0#
#343
1#
b00000000000000000000001010101100 '
b00000000000000000000001010110000 (
b00000000000000000000001010101100 )
#344
0#
#345
1#
b00000000000000000000001010110000 '
b00000000000000000000001010110100 (
b00000000000000000000001010110000 )
#346
0#
#347
1#
b00000000000000000000001010110100 '
b00000000000000000000001010111000 (
b00000000000000000000001010110100 )
#348
0#
#349
1#
b00000000000000000000001010111000 '
b00000000000000000000001010111100 (
b00000000000000000000001010111000 )
#350
0#
#351
1#
b00000000000000000000001010111100 '
b00000000000000000000001011000000 (
b00000000000000000000001010111100 )
#352
0#
#353
1#
b00000000000000000000001011000000 '
b00000000000000000000001011000100 (
b00000000000000000000001011000000 )
#354
0#
#355
1#
b00000000000000000000001011000100 '
b00000000000000000000001011001000 (
b00000000000000000000001011000100 )
#356
0#
#357
1#
b00000000000000000000001011001000 '
b00000000000000000000001011001100 (
b00000000000000000000001011001000 )
#358
0#
#359
1#
b00000000000000000000001011001100 '
b00000000000000000000001011010000 (
b00000000000000000000001011001100 )
#360
0#
#361
1#
b00000000000000000000001011010000 '
b00000000000000000000001011010100 (
b00000000000000000000001011010000 )
#362
0#
#363
1#
b00000000000000000000001011010100 '
b00000000000000000000001011011000 (
b00000000000000000000001011010100 )
#364
0#
#365
1#
b00000000000000000000001011011000 '
b00000000000000000000001011011100 (
b00000000000000000000001011011000 )
#366
0#
#367
1#
b00000000000000000000001011011100 '
b00000000000000000000001011100000 (
b00000000000000000000001011011100 )
#368
0#
#369
1#
b00000000000000000000001011100000 '
b00000000000000000000001011100100 (
b00000000000000000000001011100000 )
#370
0#
#371
1#
b00000000000000000000001011100100 '
b00000000000000000000001011101000 (
b00000000000000000000001011100100 )
#372
0#
#373
1#
b00000000000000000000001011101000 '
b00000000000000000000001011101100 (
b00000000000000000000001011101000 )
#374
0#
#375
1#
b00000000000000000000001011101100 '
b00000000000000000000001011110000 (
b00000000000000000000001011101100 )
#376
0#
#377
1#
b00000000000000000000001011110000 '
b00000000000000000000001011110100 (
b00000000000000000000001011110000 )
#378
0#
#379
1#
b00000000000000000000001011110100 '
b00000000000000000000001011111000 (
b00000000000000000000001011110100 )
#380
0#
#381
1#
b00000000000000000000001011111000 '
b00000000000000000000001011111100 (
b00000000000000000000001011111000 )
#382
0#
#383
1#
b00000000000000000000001011111100 '
b00000000000000000000001100000000 (
b00000000000000000000001011111100 )
#384
0#
#385
1#
b00000000000000000000001100000000 '
b00000000000000000000001100000100 (
b00000000000000000000001100000000 )
#386
0#
#387
1#
b00000000000000000000001100000100 '
b00000000000000000000001100001000 (
b00000000000000000000001100000100 )
#388
0#
#389
1#
b00000000000000000000001100001000 '
b00000000000000000000001100001100 (
b00000000000000000000001100001000 )
#390
0#
#391
1#
b00000000000000000000001100001100 '
b00000000000000000000001100010000 (
b00000000000000000000001100001100 )
#392
0#
#393
1#
b00000000000000000000001100010000 '
b00000000000000000000001100010100 (
b00000000000000000000001100010000 )
#394
0#
#395
1#
b00000000000000000000001100010100 '
b00000000000000000000001100011000 (
b00000000000000000000001100010100 )
#396
0#
#397
1#
b00000000000000000000001100011000 '
b00000000000000000000001100011100 (
b00000000000000000000001100011000 )
#398
0#
#399
1#
b00000000000000000000001100011100 '
b00000000000000000000001100100000 (
b00000000000000000000001100011100 )
#400
0#
#401
1#
b00000000000000000000001100100000 '
b00000000000000000000001100100100 (
b00000000000000000000001100100000 )
#402
0#
#403
1#
b00000000000000000000001100100100 '
b00000000000000000000001100101000 (
b00000000000000000000001100100100 )
#404
0#
#405
1#
b00000000000000000000001100101000 '
b00000000000000000000001100101100 (
b00000000000000000000001100101000 )
#406
0#
#407
1#
b00000000000000000000001100101100 '
b00000000000000000000001100110000 (
b00000000000000000000001100101100 )
#408
0#
#409
1#
b00000000000000000000001100110000 '
b00000000000000000000001100110100 (
b00000000000000000000001100110000 )
#410
0#
#411
1#
b00000000000000000000001100110100 '
b00000000000000000000001100111000 (
b00000000000000000000001100110100 )
#412
0#
#413
1#
b00000000000000000000001100111000 '
b00000000000000000000001100111100 (
b00000000000000000000001100111000 )
#414
0#
#415
1#
b00000000000000000000001100111100 '
b00000000000000000000001101000000 (
b00000000000000000000001100111100 )
#416
0#
#417
1#
b00000000000000000000001101000000 '
b00000000000000000000001101000100 (
b00000000000000000000001101000000 )
#418
0#
#419
1#
b00000000000000000000001101000100 '
b00000000000000000000001101001000 (
b00000000000000000000001101000100 )
#420
0#
#421
1#
b00000000000000000000001101001000 '
b00000000000000000000001101001100 (
b00000000000000000000001101001000 )
#422
0#
#423
1#
b00000000000000000000001101001100 '
b00000000000000000000001101010000 (
b00000000000000000000001101001100 )
#424
0#
#425
1#
b00000000000000000000001101010000 '
b00000000000000000000001101010100 (
b00000000000000000000001101010000 )
#426
0#
#427
1#
b00000000000000000000001101010100 '
b00000000000000000000001101011000 (
b00000000000000000000001101010100 )
#428
0#
#429
1#
b00000000000000000000001101011000 '
b00000000000000000000001101011100 (
b00000000000000000000001101011000 )
#430
0#
#431
1#
b00000000000000000000001101011100 '
b00000000000000000000001101100000 (
b00000000000000000000001101011100 )
#432
0#
#433
1#
b00000000000000000000001101100000 '
b00000000000000000000001101100100 (
b00000000000000000000001101100000 )
#434
0#
#435
1#
b00000000000000000000001101100100 '
b00000000000000000000001101101000 (
b00000000000000000000001101100100 )
#436
0#
#437
1#
b00000000000000000000001101101000 '
b00000000000000000000001101101100 (
b00000000000000000000001101101000 )
#438
0#
#439
1#
b00000000000000000000001101101100 '
b00000000000000000000001101110000 (
b00000000000000000000001101101100 )
#440
0#
#441
1#
b00000000000000000000001101110000 '
b00000000000000000000001101110100 (
b00000000000000000000001101110000 )
#442
0#
#443
1#
b00000000000000000000001101110100 '
b00000000000000000000001101111000 (
b00000000000000000000001101110100 )
#444
0#
#445
1#
b00000000000000000000001101111000 '
b00000000000000000000001101111100 (
b00000000000000000000001101111000 )
#446
0#
#447
1#
b00000000000000000000001101111100 '
b00000000000000000000001110000000 (
b00000000000000000000001101111100 )
#448
0#
#449
1#
b00000000000000000000001110000000 '
b00000000000000000000001110000100 (
b00000000000000000000001110000000 )
#450
0#
#451
1#
b00000000000000000000001110000100 '
b00000000000000000000001110001000 (
b00000000000000000000001110000100 )
#452
0#
#453
1#
b00000000000000000000001110001000 '
b00000000000000000000001110001100 (
b00000000000000000000001110001000 )
#454
0#
#455
1#
b00000000000000000000001110001100 '
b00000000000000000000001110010000 (
b00000000000000000000001110001100 )
#456
0#
#457
1#
b00000000000000000000001110010000 '
b00000000000000000000001110010100 (
b00000000000000000000001110010000 )
#458
0#
#459
1#
b00000000000000000000001110010100 '
b00000000000000000000001110011000 (
b00000000000000000000001110010100 )
#460
0#
#461
1#
b00000000000000000000001110011000 '
b00000000000000000000001110011100 (
b00000000000000000000001110011000 )
#462
0#
#463
1#
b00000000000000000000001110011100 '
b00000000000000000000001110100000 (
b00000000000000000000001110011100 )
#464
0#
#465
1#
b00000000000000000000001110100000 '
b00000000000000000000001110100100 (
b00000000000000000000001110100000 )
#466
0#
#467
1#
b00000000000000000000001110100100 '
b00000000000000000000001110101000 (
b00000000000000000000001110100100 )
#468
0#
#469
1#
b00000000000000000000001110101000 '
b00000000000000000000001110101100 (
b00000000000000000000001110101000 )
#470
0#
#471
1#
b00000000000000000000001110101100 '
b00000000000000000000001110110000 (
b00000000000000000000001110101100 )
#472
0#
#473
1#
b00000000000000000000001110110000 '
b00000000000000000000001110110100 (
b00000000000000000000001110110000 )
#474
0#
#475
1#
b00000000000000000000001110110100 '
b00000000000000000000001110111000 (
b00000000000000000000001110110100 )
#476
0#
